{"id":"beer","term":"Beer","source":"Easton's Bible Dictionary (M.G. Easton, 1897)","html":"<p>Well. (1.) A place where a well was dug by the direction of Moses, at the forty-fourth station of the Hebrews in their wanderings (<a class=\"ref\" data-ref=\"Numbers 21:16\">Num. 21:16-18</a>) in the wilderness of Moab. (See WELL.)</p>\n<p>(2.) A town in the tribe of Judah to which Jotham fled for fear of Abimelech (<a class=\"ref\" data-ref=\"Judges 9:21\">Judg. 9:21</a>). Some have identified this place with Beeroth.</p>\n\u0000","refs":["Numbers 21:16","Judges 9:21"]}