{"id":"bondage","term":"Bondage","source":"Easton's Bible Dictionary (M.G. Easton, 1897)","html":"<p>Of Israel in Egypt (<a class=\"ref\" data-ref=\"Exodus 2:23\">Ex. 2:23</a>, <a class=\"ref\" data-ref=\"Genesis 1:25\">25</a>; <a class=\"ref\" data-ref=\"Genesis 1:5\">5</a>), which is called the “house of bondage” (13:3; 20:2). This word is used also with reference to the captivity in Babylon (<a class=\"ref\" data-ref=\"Isaiah 14:3\">Isa. 14:3</a>), and the oppression of the Persian king (<a class=\"ref\" data-ref=\"Ezra 9:8\">Ezra 9:8</a>, <a class=\"ref\" data-ref=\"Ezra 9:9\">9</a>).</p>\n\u0000","refs":["Exodus 2:23","Genesis 1:25","Genesis 1:5","Isaiah 14:3","Ezra 9:8","Ezra 9:9"]}