{"id":"dor","term":"Dor","source":"Easton's Bible Dictionary (M.G. Easton, 1897)","html":"<p>Dwelling, the Dora of the Romans, an ancient royal city of the Canaanites (<a class=\"ref\" data-ref=\"Joshua 11:1\">Josh. 11:1</a>, <a class=\"ref\" data-ref=\"Genesis 1:2\">2</a>; <a class=\"ref\" data-ref=\"Genesis 13:3\">12:23</a>). It was the most southern settlement of the Phoenicians on the coast of Syria. The original inhabitants seem never to have been expelled, although they were made tributary by David. It was one of Solomon’s commissariat districts (<a class=\"ref\" data-ref=\"Judges 1:27\">Judg. 1:27</a>; <a class=\"ref\" data-ref=\"1 Kings 4:11\">1 Kings 4:11</a>). It has been identified with Tantura (so named from the supposed resemblance of its tower to a tantur, i.e., “a horn”). This tower fell in 1895, and nothing remains but debris and foundation walls, the remains of an old Crusading fortress. It is about 8 miles north of Caesarea, “a sad and sickly hamlet of wretched huts on a naked sea-beach.”</p>\n\u0000","refs":["Joshua 11:1","Genesis 1:2","Genesis 13:3","Judges 1:27","1 Kings 4:11"]}