{"id":"jahath","term":"Jahath","source":"Easton's Bible Dictionary (M.G. Easton, 1897)","html":"<p>Union. (1.) A son of Shimei, and grandson of Gershom (<a class=\"ref\" data-ref=\"1 Chronicles 23:10\">1 Chr. 23:10</a>).</p>\n<p>(2.) One of the sons of Shelomoth, of the family of Kohath (<a class=\"ref\" data-ref=\"1 Chronicles 24:22\">1 Chr. 24:22</a>).</p>\n<p>(3.) A Levite of the family of Merari, one of the overseers of the repairs of the temple under Josiah (<a class=\"ref\" data-ref=\"2 Chronicles 34:12\">2 Chr. 34:12</a>).</p>\n\u0000","refs":["1 Chronicles 23:10","1 Chronicles 24:22","2 Chronicles 34:12"]}