{"id":"kenizzite","term":"Kenizzite","source":"Easton's Bible Dictionary (M.G. Easton, 1897)","html":"<p>(1.) The name of a tribe referred to in the covenant God made with Abraham (<a class=\"ref\" data-ref=\"Genesis 15:19\">Gen. 15:19</a>). They are not mentioned among the original inhabitants of Canaan (<a class=\"ref\" data-ref=\"Exodus 3:8\">Ex. 3:8</a>; <a class=\"ref\" data-ref=\"Joshua 3:10\">Josh. 3:10</a>), and probably they inhabited some part of Arabia, in the confines of Syria.</p>\n<p>(2.) A designation given to Caleb (R.V., <a class=\"ref\" data-ref=\"Numbers 32:12\">Num. 32:12</a>; A.V., Kenezite).</p>\n\u0000","refs":["Genesis 15:19","Exodus 3:8","Joshua 3:10","Numbers 32:12"]}