{"id":"malluch","term":"Malluch","source":"Easton's Bible Dictionary (M.G. Easton, 1897)","html":"<p>Reigned over, or reigning. (1.) A Levite of the family of Merari (<a class=\"ref\" data-ref=\"1 Chronicles 6:44\">1 Chr. 6:44</a>).</p>\n<p>(2.) A priest who returned from Babylon (<a class=\"ref\" data-ref=\"Nehemiah 12:2\">Neh. 12:2</a>).</p>\n<p>(3.) <a class=\"ref\" data-ref=\"Ezra 10:29\">Ezra 10:29</a>. (4.) <a class=\"ref\" data-ref=\"Ezra 10:32\">Ezra 10:32</a></p>\n\u0000","refs":["1 Chronicles 6:44","Nehemiah 12:2","Ezra 10:29","Ezra 10:32"]}