{"id":"benjamin","term":"Benjamin","category":"people","intro":"<p>Benjamin (meaning <em>son of my right hand</em>; his dying mother Rachel called him Ben-oni, <em>son of my sorrow</em>) was the youngest son of Jacob, the only one born in Canaan, and the full brother of Joseph. His birth cost Rachel her life (Genesis 35:18). Jacob clung to Benjamin after Joseph's disappearance, and the story of Joseph's test of his brothers revolves around Benjamin's detention in Egypt. Jacob's dying blessing describes Benjamin as a <em>ravenous wolf</em> (Genesis 49:27), a prophecy reflected in the tribe's fierce warriors, including Ehud, Saul, and Jonathan.</p><p>The tribe of Benjamin occupied a small but strategically vital territory between Judah and Ephraim, including Jerusalem's suburbs, Jericho, Bethel, and Gibeah. After the kingdom's division, Benjamin aligned with Judah. Paul identifies himself as <em>of the tribe of Benjamin</em> (Philippians 3:5; Romans 11:1).</p>","hitchcock_meaning":"son of the right hand","source_ids":{"easton":"benjamin","smith":"benjamin","isbe":"benjamin"},"key_refs":["Genesis 35:18","Genesis 49:27","Joshua 18:21","Philippians 3:5"],"sections":[],"nave_slugs":["benjamin"]}