{"id":"jah","term":"Jah","category":"concepts","intro":"<p>Jah is a poetic contraction of <em>YHWH</em> (Yahweh), the covenant name of Israel's God, used especially in poetry and doxology. It appears 49 times in the Hebrew Bible, most frequently in the Psalms, and is embedded in the exclamation <em>Hallelujah</em> (\"praise Yah\"). The form appears explicitly in Psalm 68:4: \"Extol him that rideth upon the heavens by his name JAH, and rejoice before him.\" It also appears in compound names like Elijah (<em>Eliyahu</em>, \"my God is Yah\"), Isaiah (<em>Yesha'yahu</em>, \"salvation of Yah\"), and Jeremiah (<em>Yirmeyahu</em>). The name points to the eternal, self-existent being of God — the One who IS.</p>","hitchcock_meaning":"the everlasting","source_ids":{"easton":"jah"},"key_refs":["Psalms 68:4","Revelation 19:1"],"sections":[],"nave_slugs":[]}