{"id":"zimmah","term":"Zimmah","category":"people","intro":"<p>Zimmah (meaning: <em>thought; wickedness</em>) is the name of several Gershonite Levites in the genealogies of Chronicles. (1.) A Gershonite Levite in the lineage recorded in <strong>1 Chronicles 6:20</strong>. (2.) Another Gershonite Levite appearing in a parallel genealogy at <strong>1 Chronicles 6:42</strong>. (3.) The father of Joah, who was one of the Levites who assisted Hezekiah in the cleansing of the temple (<strong>2 Chr. 29:12</strong>).</p><p>The presence of the same name at several points in the Gershonite lineage is consistent with the pattern of reusing ancestral names across generations. The Joah son of Zimmah who served under Hezekiah represents the family's continued Levitical service in the era of temple reform.</p>","sections":[],"hitchcock_meaning":"thought; wickedness","source_ids":["easton"],"key_refs":["1 Chronicles 6:20","1 Chronicles 6:42","2 Chronicles 29:12"],"nave_slugs":["zimmah"]}