{
  "1": {
    "breaks": [
      {
        "v": 1,
        "type": "narrative"
      },
      {
        "v": 4,
        "type": "narrative"
      },
      {
        "v": 15,
        "type": "narrative"
      },
      {
        "v": 22,
        "type": "narrative"
      }
    ],
    "headings": [
      {
        "before": 1,
        "text": "Introduction"
      },
      {
        "before": 4,
        "text": "The Four Living Creatures"
      },
      {
        "before": 15,
        "text": "The Wheels"
      },
      {
        "before": 22,
        "text": "The Throne of God"
      }
    ]
  },
  "2": {
    "breaks": [
      {
        "v": 1,
        "type": "dialogue"
      },
      {
        "v": 6,
        "type": "dialogue"
      }
    ],
    "headings": [
      {
        "before": 1,
        "text": "Ezekiel's Call"
      },
      {
        "before": 6,
        "text": "The Scroll Given"
      }
    ]
  },
  "3": {
    "breaks": [
      {
        "v": 1,
        "type": "dialogue"
      },
      {
        "v": 12,
        "type": "dialogue"
      },
      {
        "v": 22,
        "type": "narrative"
      }
    ],
    "headings": [
      {
        "before": 1,
        "text": "Eat the Scroll"
      },
      {
        "before": 12,
        "text": "Ezekiel as Watchman"
      },
      {
        "before": 22,
        "text": "Confined and Silenced"
      }
    ]
  },
  "4": {
    "breaks": [
      {
        "v": 1,
        "type": "narrative"
      },
      {
        "v": 9,
        "type": "narrative"
      }
    ],
    "headings": [
      {
        "before": 1,
        "text": "The Siege of Jerusalem"
      },
      {
        "before": 9,
        "text": "Rationed Food"
      }
    ]
  },
  "5": {
    "breaks": [
      {
        "v": 1,
        "type": "narrative"
      },
      {
        "v": 5,
        "type": "dialogue"
      }
    ],
    "headings": [
      {
        "before": 1,
        "text": "The Razor Sign"
      },
      {
        "before": 5,
        "text": "Judgment on Jerusalem"
      }
    ]
  },
  "6": {
    "breaks": [
      {
        "v": 1,
        "type": "poetry"
      },
      {
        "v": 8,
        "type": "dialogue"
      },
      {
        "v": 11,
        "type": "dialogue"
      }
    ],
    "headings": [
      {
        "before": 1,
        "text": "Against the Mountains of Israel"
      },
      {
        "before": 8,
        "text": "A Remnant Preserved"
      },
      {
        "before": 11,
        "text": "Judgment on the High Places"
      }
    ]
  },
  "7": {
    "breaks": [
      {
        "v": 1,
        "type": "poetry"
      },
      {
        "v": 10,
        "type": "poetry"
      },
      {
        "v": 23,
        "type": "dialogue"
      }
    ],
    "headings": [
      {
        "before": 1,
        "text": "The End Has Come"
      },
      {
        "before": 10,
        "text": "Doom on Every Side"
      },
      {
        "before": 23,
        "text": "Utter Ruin"
      }
    ]
  },
  "8": {
    "breaks": [
      {
        "v": 1,
        "type": "narrative"
      },
      {
        "v": 5,
        "type": "narrative"
      },
      {
        "v": 14,
        "type": "narrative"
      }
    ],
    "headings": [
      {
        "before": 1,
        "text": "Vision of Jerusalem's Abominations"
      },
      {
        "before": 5,
        "text": "Idolatry in the Temple"
      },
      {
        "before": 14,
        "text": "Worse Abominations"
      }
    ]
  },
  "9": {
    "breaks": [
      {
        "v": 1,
        "type": "narrative"
      },
      {
        "v": 8,
        "type": "dialogue"
      }
    ],
    "headings": [
      {
        "before": 1,
        "text": "The Slaughter of the Wicked"
      },
      {
        "before": 8,
        "text": "Ezekiel's Intercession"
      }
    ]
  },
  "10": {
    "breaks": [
      {
        "v": 1,
        "type": "narrative"
      },
      {
        "v": 8,
        "type": "narrative"
      },
      {
        "v": 18,
        "type": "narrative"
      }
    ],
    "headings": [
      {
        "before": 1,
        "text": "Coals of Fire"
      },
      {
        "before": 8,
        "text": "The Cherubim and Wheels"
      },
      {
        "before": 18,
        "text": "The Glory Departs the Temple"
      }
    ]
  },
  "11": {
    "breaks": [
      {
        "v": 1,
        "type": "narrative"
      },
      {
        "v": 14,
        "type": "dialogue"
      },
      {
        "v": 22,
        "type": "narrative"
      }
    ],
    "headings": [
      {
        "before": 1,
        "text": "Judgment on Wicked Leaders"
      },
      {
        "before": 14,
        "text": "Promise of Restoration"
      },
      {
        "before": 22,
        "text": "The Glory Departs Jerusalem"
      }
    ]
  },
  "12": {
    "breaks": [
      {
        "v": 1,
        "type": "narrative"
      },
      {
        "v": 17,
        "type": "narrative"
      },
      {
        "v": 21,
        "type": "dialogue"
      }
    ],
    "headings": [
      {
        "before": 1,
        "text": "Sign of the Exile"
      },
      {
        "before": 17,
        "text": "Eating with Trembling"
      },
      {
        "before": 21,
        "text": "The Time Is Near"
      }
    ]
  },
  "13": {
    "breaks": [
      {
        "v": 1,
        "type": "dialogue"
      },
      {
        "v": 10,
        "type": "dialogue"
      },
      {
        "v": 17,
        "type": "dialogue"
      }
    ],
    "headings": [
      {
        "before": 1,
        "text": "Against False Prophets"
      },
      {
        "before": 10,
        "text": "Whitewashing the Wall"
      },
      {
        "before": 17,
        "text": "Against False Prophetesses"
      }
    ]
  },
  "14": {
    "breaks": [
      {
        "v": 1,
        "type": "dialogue"
      },
      {
        "v": 12,
        "type": "dialogue"
      },
      {
        "v": 21,
        "type": "dialogue"
      }
    ],
    "headings": [
      {
        "before": 1,
        "text": "Idols in the Heart"
      },
      {
        "before": 12,
        "text": "Four Sore Judgments"
      },
      {
        "before": 21,
        "text": "A Remnant Will Come"
      }
    ]
  },
  "15": {
    "breaks": [
      {
        "v": 1,
        "type": "poetry"
      },
      {
        "v": 6,
        "type": "dialogue"
      }
    ],
    "headings": [
      {
        "before": 1,
        "text": "The Useless Vine"
      },
      {
        "before": 6,
        "text": "Jerusalem Is Like the Vine"
      }
    ]
  },
  "16": {
    "breaks": [
      {
        "v": 1,
        "type": "poetry"
      },
      {
        "v": 15,
        "type": "poetry"
      },
      {
        "v": 35,
        "type": "dialogue"
      },
      {
        "v": 44,
        "type": "dialogue"
      },
      {
        "v": 59,
        "type": "dialogue"
      }
    ],
    "headings": [
      {
        "before": 1,
        "text": "Jerusalem's Origins"
      },
      {
        "before": 15,
        "text": "Jerusalem's Unfaithfulness"
      },
      {
        "before": 35,
        "text": "Judgment on Jerusalem"
      },
      {
        "before": 44,
        "text": "Worse Than Sodom"
      },
      {
        "before": 59,
        "text": "The Eternal Covenant"
      }
    ]
  },
  "17": {
    "breaks": [
      {
        "v": 1,
        "type": "poetry"
      },
      {
        "v": 11,
        "type": "dialogue"
      },
      {
        "v": 22,
        "type": "poetry"
      }
    ],
    "headings": [
      {
        "before": 1,
        "text": "The Parable of Two Eagles"
      },
      {
        "before": 11,
        "text": "Explanation of the Parable"
      },
      {
        "before": 22,
        "text": "God Plants the High Cedar"
      }
    ]
  },
  "18": {
    "breaks": [
      {
        "v": 1,
        "type": "dialogue"
      },
      {
        "v": 19,
        "type": "dialogue"
      },
      {
        "v": 25,
        "type": "dialogue"
      }
    ],
    "headings": [
      {
        "before": 1,
        "text": "The Soul Who Sins"
      },
      {
        "before": 19,
        "text": "Each Person's Responsibility"
      },
      {
        "before": 25,
        "text": "God's Ways Are Just"
      }
    ]
  },
  "19": {
    "breaks": [
      {
        "v": 1,
        "type": "poetry"
      },
      {
        "v": 10,
        "type": "poetry"
      }
    ],
    "headings": [
      {
        "before": 1,
        "text": "A Lament for Israel's Princes"
      },
      {
        "before": 10,
        "text": "The Vine and Its Destruction"
      }
    ]
  },
  "20": {
    "breaks": [
      {
        "v": 1,
        "type": "dialogue"
      },
      {
        "v": 9,
        "type": "dialogue"
      },
      {
        "v": 33,
        "type": "dialogue"
      },
      {
        "v": 45,
        "type": "poetry"
      }
    ],
    "headings": [
      {
        "before": 1,
        "text": "Israel's Rebellion in Egypt"
      },
      {
        "before": 9,
        "text": "Wilderness Rebellion"
      },
      {
        "before": 33,
        "text": "Future Restoration"
      },
      {
        "before": 45,
        "text": "Fire in the South"
      }
    ]
  },
  "21": {
    "breaks": [
      {
        "v": 1,
        "type": "poetry"
      },
      {
        "v": 8,
        "type": "poetry"
      },
      {
        "v": 18,
        "type": "dialogue"
      },
      {
        "v": 28,
        "type": "poetry"
      }
    ],
    "headings": [
      {
        "before": 1,
        "text": "The Drawn Sword"
      },
      {
        "before": 8,
        "text": "The Sword Song"
      },
      {
        "before": 18,
        "text": "The King of Babylon at the Fork"
      },
      {
        "before": 28,
        "text": "Oracle Against Ammon"
      }
    ]
  },
  "22": {
    "breaks": [
      {
        "v": 1,
        "type": "dialogue"
      },
      {
        "v": 17,
        "type": "poetry"
      },
      {
        "v": 23,
        "type": "dialogue"
      }
    ],
    "headings": [
      {
        "before": 1,
        "text": "Jerusalem's Bloody Sins"
      },
      {
        "before": 17,
        "text": "Israel Like Dross"
      },
      {
        "before": 23,
        "text": "Every Class Has Failed"
      }
    ]
  },
  "23": {
    "breaks": [
      {
        "v": 1,
        "type": "dialogue"
      },
      {
        "v": 11,
        "type": "dialogue"
      },
      {
        "v": 22,
        "type": "dialogue"
      },
      {
        "v": 36,
        "type": "dialogue"
      }
    ],
    "headings": [
      {
        "before": 1,
        "text": "Oholah, the Unfaithful Sister"
      },
      {
        "before": 11,
        "text": "Oholibah, More Corrupt"
      },
      {
        "before": 22,
        "text": "Judgment on Oholibah"
      },
      {
        "before": 36,
        "text": "Their Crimes and Punishment"
      }
    ]
  },
  "24": {
    "breaks": [
      {
        "v": 1,
        "type": "narrative"
      },
      {
        "v": 15,
        "type": "narrative"
      }
    ],
    "headings": [
      {
        "before": 1,
        "text": "The Boiling Pot"
      },
      {
        "before": 15,
        "text": "Death of Ezekiel's Wife"
      }
    ]
  }
}