{
  "1": {
    "breaks": [
      {
        "v": 1,
        "type": "narrative"
      },
      {
        "v": 2,
        "type": "poetry"
      },
      {
        "v": 8,
        "type": "poetry"
      },
      {
        "v": 10,
        "type": "poetry"
      }
    ],
    "headings": [
      {
        "before": 1,
        "text": "Superscription"
      },
      {
        "before": 2,
        "text": "Judgment on Samaria and Jerusalem"
      },
      {
        "before": 8,
        "text": "Micah's Lament"
      },
      {
        "before": 10,
        "text": "Mourning for the Cities of Judah"
      }
    ]
  },
  "2": {
    "breaks": [
      {
        "v": 1,
        "type": "poetry"
      },
      {
        "v": 6,
        "type": "dialogue"
      },
      {
        "v": 12,
        "type": "poetry"
      }
    ],
    "headings": [
      {
        "before": 1,
        "text": "Woe to the Oppressors"
      },
      {
        "before": 6,
        "text": "False Prophets Rebuked"
      },
      {
        "before": 12,
        "text": "The Remnant Gathered"
      }
    ]
  },
  "3": {
    "breaks": [
      {
        "v": 1,
        "type": "dialogue"
      },
      {
        "v": 5,
        "type": "dialogue"
      },
      {
        "v": 8,
        "type": "narrative"
      },
      {
        "v": 9,
        "type": "dialogue"
      }
    ],
    "headings": [
      {
        "before": 1,
        "text": "Rulers and Prophets Condemned"
      },
      {
        "before": 5,
        "text": "False Prophets"
      },
      {
        "before": 9,
        "text": "Jerusalem's Destruction Foretold"
      }
    ]
  },
  "4": {
    "breaks": [
      {
        "v": 1,
        "type": "poetry"
      },
      {
        "v": 6,
        "type": "poetry"
      },
      {
        "v": 9,
        "type": "dialogue"
      }
    ],
    "headings": [
      {
        "before": 1,
        "text": "The Mountain of the LORD"
      },
      {
        "before": 6,
        "text": "The Remnant Restored"
      },
      {
        "before": 9,
        "text": "Present Distress and Future Deliverance"
      }
    ]
  },
  "5": {
    "breaks": [
      {
        "v": 1,
        "type": "dialogue"
      },
      {
        "v": 2,
        "type": "poetry"
      },
      {
        "v": 5,
        "type": "poetry"
      },
      {
        "v": 7,
        "type": "poetry"
      },
      {
        "v": 10,
        "type": "poetry"
      }
    ],
    "headings": [
      {
        "before": 1,
        "text": "The Siege of Jerusalem"
      },
      {
        "before": 2,
        "text": "The Ruler from Bethlehem"
      },
      {
        "before": 5,
        "text": "Deliverance from Assyria"
      },
      {
        "before": 7,
        "text": "The Remnant among the Nations"
      },
      {
        "before": 10,
        "text": "Purification of the Land"
      }
    ]
  },
  "6": {
    "breaks": [
      {
        "v": 1,
        "type": "dialogue"
      },
      {
        "v": 6,
        "type": "dialogue"
      },
      {
        "v": 9,
        "type": "dialogue"
      }
    ],
    "headings": [
      {
        "before": 1,
        "text": "The LORD's Case Against Israel"
      },
      {
        "before": 6,
        "text": "What God Requires"
      },
      {
        "before": 9,
        "text": "Punishment for Wickedness"
      }
    ]
  },
  "7": {
    "breaks": [
      {
        "v": 1,
        "type": "poetry"
      },
      {
        "v": 7,
        "type": "poetry"
      },
      {
        "v": 11,
        "type": "poetry"
      },
      {
        "v": 14,
        "type": "dialogue"
      },
      {
        "v": 18,
        "type": "doxology"
      }
    ],
    "headings": [
      {
        "before": 1,
        "text": "Micah's Lament"
      },
      {
        "before": 7,
        "text": "Hope in God"
      },
      {
        "before": 11,
        "text": "Restoration Promised"
      },
      {
        "before": 14,
        "text": "Prayer for God's People"
      },
      {
        "before": 18,
        "text": "God's Steadfast Love"
      }
    ]
  }
}