{"id":"concerning","term":"Concerning","source":"International Standard Bible Encyclopaedia (James Orr ed., 1915)","html":"<p>kon-surn'-ing:</p><p>The Revised Version (British and American) makes frequent changes, such as \"for,\" \"as for,\" \"from,\" \"about,\" for \"concerning\"; \"concerning\" instead of \"for,\" \"of,\" \"over,\" \"in,\" \"against,\" etc. Some of the other changes are, \"unto that which is good\" for \"concerning\" (<a class=\"ref\" data-ref=\"Romans 16:19\">Ro 16:19</a>), \"concerning\" instead of \"because of\" (<a class=\"ref\" data-ref=\"Jeremiah 23:9\">Jer 23:9</a>), for \"the miracle of\" (<a class=\"ref\" data-ref=\"Mark 6:52\">Mr 6:52</a>); for \"with\" (<a class=\"ref\" data-ref=\"Mark 10:41\">Mr 10:41</a>), for \"of the Lord\" (<a class=\"ref\" data-ref=\"Acts 18:25\">Ac 18:25</a>), \"concerning Jesus\" (diferent text), \"by way of disparagement\" (<a class=\"ref\" data-ref=\"2 Corinthians 11:21\">2Co 11:21</a>), instead of \"concerning reproach\"; \"Why askest thou me concerning that which is good?\" (<a class=\"ref\" data-ref=\"Matthew 19:17\">Mt 19:17</a>) instead of \"Why callest thou me good?\" (different text; see the Revised Version, margin).</p><p>W. L. Walker</p>\n\u0000","refs":["Romans 16:19","Jeremiah 23:9","Mark 6:52","Mark 10:41","Acts 18:25","2 Corinthians 11:21","Matthew 19:17"]}