{"id":"jeatherai-jeaterai","term":"Jeatherai; Jeaterai","source":"International Standard Bible Encyclopaedia (James Orr ed., 1915)","html":"<p>je-ath'-e-ri, jeat'-e-ri (Revised Version (British and American)), (the King James Version) (ye'atheray, meaning unknown): A descendant of Gershom, \"son\" of Levi (<a class=\"ref\" data-ref=\"1 Chronicles 6:21\">1Ch 6:21</a> (<a class=\"ref\" data-ref=\"Hebrews 6:1\">Hebrew 6</a>)), and probably an ancestor of Asaph (so commentators); in 6:39-43 the corresponding name is \"Ei.\" The difference in the Hebrew words is not great.</p>\n\u0000","refs":["1 Chronicles 6:21","Hebrews 6:1"]}