{"id":"plain-of-the-pillar","term":"Plain Of The Pillar","source":"International Standard Bible Encyclopaedia (James Orr ed., 1915)","html":"<p>('elon mutstsbh; Codex Vaticanus reads pros te balano te heurete tes staseos tes en Sikimois; Codex Alexandrinus omits te heurete, and the second tes): With the Revised Version margin we must read \"terebinth of the pillar,\" the place where the men of Shechem and Beth-millo made Abimelech king (<a class=\"ref\" data-ref=\"Judges 9:6\">Jud 9:6</a>). This was one of the sacred trees of which there seem to have been several near Shechem. See MEONENIM, OAK OF. \"The pillar\" may possibly have been the great stone which Joshua set up \"under the oak that was by the sanctuary of Yahweh\" (<a class=\"ref\" data-ref=\"Joshua 24:26\">Jos 24:26</a>).</p><p>W. Ewing</p>\n\u0000","refs":["Judges 9:6","Joshua 24:26"]}