{
  "chapters": {
    "1": {
      "1": "The|strong=\"H0834\"word|strong=\"H1697\"of|strong=\"H4428\"the|strong=\"H0834\"Lord|strong=\"H3068\"that|strong=\"H0834\"came|strong=\"H1961\"to|strong=\"H0413\"Micheas the|strong=\"H0834\"Morasthite, in|strong=\"H5921\"the|strong=\"H0834\"days|strong=\"H3117\"of|strong=\"H4428\"Joathan, Achaz, and|strong=\"H3068\"Ezechias, kings|strong=\"H4428\"of|strong=\"H4428\"Juda: which|strong=\"H0834\"he|strong=\"H0834\"saw|strong=\"H2372\"concerning|strong=\"H5921\"Samaria|strong=\"H8111\"and|strong=\"H3068\"Jerusalem|strong=\"H3389\".",
      "2": "Hear|strong=\"H8085\", all|strong=\"H3605\"ye people|strong=\"H5971\": and|strong=\"H0776\"let|strong=\"H1961\"the|strong=\"H3605\"earth|strong=\"H0776\"give|strong=\"H7181\"ear, and|strong=\"H0776\"all|strong=\"H3605\"that|strong=\"H3605\"is|strong=\"H0776\"therein: and|strong=\"H0776\"let|strong=\"H1961\"the|strong=\"H3605\"Lord|strong=\"H0136\"God|strong=\"H0136\"be|strong=\"H1961\"a|strong=\"H1961\"witness|strong=\"H5707\"to|strong=\"H1961\"you|strong=\"H3605\", the|strong=\"H3605\"Lord|strong=\"H0136\"from|strong=\"H8085\"his|strong=\"H3605\"holy|strong=\"H6944\"temple|strong=\"H1964\".",
      "3": "For|strong=\"H3588\"behold|strong=\"H2009\"the|strong=\"H5921\"Lord|strong=\"H3068\"will|strong=\"H3068\"come|strong=\"H3318\"forth|strong=\"H3318\"out|strong=\"H3318\"of|strong=\"H0776\"his|strong=\"H5921\"place|strong=\"H4725\": and|strong=\"H3068\"he|strong=\"H3588\"will|strong=\"H3068\"come|strong=\"H3318\"down|strong=\"H3381\", and|strong=\"H3068\"will|strong=\"H3068\"tread|strong=\"H1869\"upon|strong=\"H5921\"the|strong=\"H5921\"high|strong=\"H1116\"places|strong=\"H1116\"of|strong=\"H0776\"the|strong=\"H5921\"earth|strong=\"H0776\".",
      "4": "And|strong=\"H6440\"the|strong=\"H6440\"mountains|strong=\"H2022\"shall|strong=\"H8478\"be|strong=\"H4325\"melted|strong=\"H4549\"under|strong=\"H8478\"him|strong=\"H6440\": and|strong=\"H6440\"the|strong=\"H6440\"valleys|strong=\"H6010\"shall|strong=\"H8478\"be|strong=\"H4325\"cleft, as|strong=\"H8478\"wax|strong=\"H1749\"before|strong=\"H6440\"the|strong=\"H6440\"fire|strong=\"H0784\", and|strong=\"H6440\"as|strong=\"H8478\"waters|strong=\"H4325\"that|strong=\"H4325\"run down|strong=\"H5064\"a|strong=\"H8478\"steep|strong=\"H4174\"place|strong=\"H8478\".",
      "5": "For|strong=\"H1004\"the|strong=\"H3605\"wickedness of|strong=\"H1004\"Jacob|strong=\"H3290\"is|strong=\"H4310\"all|strong=\"H3605\"this|strong=\"H2063\", and|strong=\"H3063\"for|strong=\"H1004\"the|strong=\"H3605\"sins|strong=\"H2403\"of|strong=\"H1004\"the|strong=\"H3605\"house|strong=\"H1004\"of|strong=\"H1004\"Israel|strong=\"H3478\". What|strong=\"H4310\"is|strong=\"H4310\"the|strong=\"H3605\"wickedness of|strong=\"H1004\"Jacob|strong=\"H3290\"? is|strong=\"H4310\"it|strong=\"H3808\"not|strong=\"H3808\"Samaria|strong=\"H8111\"? and|strong=\"H3063\"what|strong=\"H4310\"are|strong=\"H3478\"the|strong=\"H3605\"high|strong=\"H1116\"places|strong=\"H1116\"of|strong=\"H1004\"Juda? are|strong=\"H3478\"they|strong=\"H3808\"not|strong=\"H3808\"Jerusalem|strong=\"H3389\"?",
      "6": "And|strong=\"H0068\"I|strong=\"H7760\"will|strong=\"H7704\"make|strong=\"H7760\"Samaria|strong=\"H8111\"as|strong=\"H7760\"a|strong=\"H7760\"heap|strong=\"H5856\"of|strong=\"H7704\"stones|strong=\"H0068\"in|strong=\"H0068\"the|strong=\"H7760\"field|strong=\"H7704\"when|strong=\"H1540\"a|strong=\"H7760\"vineyard|strong=\"H3754\"is|strong=\"H7704\"planted|strong=\"H4302\": and|strong=\"H0068\"I|strong=\"H7760\"will|strong=\"H7704\"bring|strong=\"H7760\"down|strong=\"H5064\"the|strong=\"H7760\"stones|strong=\"H0068\"thereof into|strong=\"H1540\"the|strong=\"H7760\"valley|strong=\"H1516\", and|strong=\"H0068\"will|strong=\"H7704\"lay|strong=\"H7760\"her|strong=\"H1540\"foundations|strong=\"H3247\"bare|strong=\"H1540\".",
      "7": "And|strong=\"H7725\"all|strong=\"H3605\"her|strong=\"H3605\"graven|strong=\"H6456\"things|strong=\"H3605\"shall be|strong=\"H7725\"cut in|strong=\"H0784\"pieces|strong=\"H3807\", and|strong=\"H7725\"all|strong=\"H3605\"her|strong=\"H3605\"wages|strong=\"H0868\"shall be|strong=\"H7725\"burnt|strong=\"H8313\"with|strong=\"H8313\"fire|strong=\"H0784\", and|strong=\"H7725\"I|strong=\"H3588\"will|strong=\"H0784\"bring|strong=\"H7725\"to|strong=\"H5704\"destruction all|strong=\"H3605\"her|strong=\"H3605\"idols|strong=\"H6091\": for|strong=\"H3588\"they|strong=\"H3588\"were|strong=\"H0784\"gathered|strong=\"H6908\"together|strong=\"H6908\"of|strong=\"H3605\"the|strong=\"H3605\"hire|strong=\"H0868\"of|strong=\"H3605\"a|strong=\"H3588\"harlot|strong=\"H2181\", and|strong=\"H7725\"unto the|strong=\"H3605\"hire|strong=\"H0868\"of|strong=\"H3605\"a|strong=\"H3588\"harlot|strong=\"H2181\"they|strong=\"H3588\"shall return|strong=\"H7725\".",
      "8": "Therefore will|strong=\"H1323\"I|strong=\"H5921\"lament|strong=\"H5594\"and|strong=\"H1323\"howl|strong=\"H3213\": I|strong=\"H5921\"will|strong=\"H1323\"go stripped and|strong=\"H1323\"naked|strong=\"H6174\": I|strong=\"H5921\"will|strong=\"H1323\"make|strong=\"H6213\"a|strong=\"H5921\"wailing|strong=\"H4553\"like|strong=\"H1323\"the|strong=\"H5921\"dragons, and|strong=\"H1323\"a|strong=\"H5921\"mourning|strong=\"H0060\"like|strong=\"H1323\"the|strong=\"H5921\"ostriches|strong=\"H3284\".",
      "9": "Because|strong=\"H3588\"her|strong=\"H0935\"wound|strong=\"H4347\"is|strong=\"H4347\"desperate, because|strong=\"H3588\"it|strong=\"H3588\"is|strong=\"H4347\"come|strong=\"H0935\"even|strong=\"H5704\"to|strong=\"H0935\"Juda, it|strong=\"H3588\"hath touched|strong=\"H5060\"the|strong=\"H3588\"gate|strong=\"H8179\"of|strong=\"H8179\"my|strong=\"H0935\"people|strong=\"H5971\"even|strong=\"H5704\"to|strong=\"H0935\"Jerusalem|strong=\"H3389\".",
      "10": "Declare|strong=\"H5046\"ye it not|strong=\"H0408\"in|strong=\"H5046\"Geth, weep|strong=\"H1058\"ye not|strong=\"H0408\"with tears: in|strong=\"H5046\"the|strong=\"H5046\"house of|strong=\"H6083\"Dust|strong=\"H6083\"sprinkle yourselves with dust|strong=\"H6083\".",
      "11": "And|strong=\"H3318\"pass|strong=\"H5674\"away|strong=\"H3947\", O thou that|strong=\"H4480\"dwellest in|strong=\"H3427\"the|strong=\"H4480\"Beautiful place, covered with|strong=\"H3427\"thy shame|strong=\"H1322\": she|strong=\"H3808\"went|strong=\"H3318\"not|strong=\"H3808\"forth|strong=\"H3318\"that|strong=\"H4480\"dwelleth in|strong=\"H3427\"the|strong=\"H4480\"confines: the|strong=\"H4480\"House adjoining shall|strong=\"H3808\"receive|strong=\"H3947\"mourning from|strong=\"H4480\"you|strong=\"H3808\", which stood by|strong=\"H3427\"herself.",
      "12": "For|strong=\"H3588\"she|strong=\"H3588\"is|strong=\"H3068\"become weak unto good|strong=\"H2896\"that|strong=\"H3588\"dwelleth in|strong=\"H3427\"bitterness: for|strong=\"H3588\"evil|strong=\"H7451\"is|strong=\"H3068\"come|strong=\"H3381\"down|strong=\"H3381\"from|strong=\"H3381\"the|strong=\"H3588\"Lord|strong=\"H3068\"into|strong=\"H3381\"the|strong=\"H3588\"gate|strong=\"H8179\"of|strong=\"H3068\"Jerusalem|strong=\"H3389\".",
      "13": "A|strong=\"H3588\"tumult of|strong=\"H1323\"chariots|strong=\"H4818\"hath astonished the|strong=\"H3588\"inhabitants|strong=\"H3427\"of|strong=\"H1323\"Lachis: it|strong=\"H1931\"is|strong=\"H1931\"the|strong=\"H3588\"beginning|strong=\"H7225\"of|strong=\"H1323\"sin|strong=\"H2403\"to|strong=\"H3478\"the|strong=\"H3588\"daughter|strong=\"H1323\"of|strong=\"H1323\"Sion, for|strong=\"H3588\"in|strong=\"H3427\"thee were|strong=\"H3478\"found|strong=\"H4672\"the|strong=\"H3588\"crimes|strong=\"H6588\"of|strong=\"H1323\"Israel|strong=\"H3478\".",
      "14": "Therefore|strong=\"H3651\"shall|strong=\"H3478\"she|strong=\"H3651\"send|strong=\"H5414\"messengers to|strong=\"H5921\"the|strong=\"H5921\"inheritance of|strong=\"H4428\"Geth: the|strong=\"H5921\"houses|strong=\"H1004\"of|strong=\"H4428\"lying to|strong=\"H5921\"deceive the|strong=\"H5921\"kings|strong=\"H4428\"of|strong=\"H4428\"Israel|strong=\"H3478\".",
      "15": "Yet|strong=\"H5750\"will|strong=\"H3478\"I|strong=\"H5704\"bring|strong=\"H0935\"an|strong=\"H0935\"heir|strong=\"H3423\"to|strong=\"H0935\"thee that|strong=\"H3478\"dwellest in|strong=\"H3427\"Maresa: even|strong=\"H5704\"to|strong=\"H0935\"Odollam shall|strong=\"H3478\"the|strong=\"H0935\"glory|strong=\"H3519\"of|strong=\"H3427\"Israel|strong=\"H3478\"come|strong=\"H0935\".",
      "16": "Make|strong=\"H7139\"thee bald|strong=\"H7144\", and|strong=\"H1121\"be|strong=\"H1121\"polled for|strong=\"H3588\"thy delicate children|strong=\"H1121\": enlarge|strong=\"H7337\"thy baldness|strong=\"H7144\"as|strong=\"H1121\"the|strong=\"H5921\"eagle|strong=\"H5404\": for|strong=\"H3588\"they|strong=\"H3588\"are|strong=\"H1121\"carried|strong=\"H1540\"into|strong=\"H1540\"captivity|strong=\"H1540\"from|strong=\"H4480\"thee."
    },
    "2": {
      "1": "Woe|strong=\"H1945\"to|strong=\"H5921\"you|strong=\"H3588\"that|strong=\"H3588\"devise|strong=\"H2803\"that|strong=\"H3588\"which is|strong=\"H3426\"unprofitable, and|strong=\"H3027\"work|strong=\"H6466\"evil|strong=\"H7451\"in|strong=\"H5921\"your|strong=\"H5921\"beds|strong=\"H4904\": in|strong=\"H5921\"the|strong=\"H5921\"morning|strong=\"H1242\"light|strong=\"H0216\"they|strong=\"H3588\"execute|strong=\"H2803\"it|strong=\"H5921\", because|strong=\"H3588\"their|strong=\"H5921\"hand|strong=\"H3027\"is|strong=\"H3426\"against|strong=\"H5921\"God|strong=\"H0410\".",
      "2": "And|strong=\"H1004\"they|strong=\"H0376\"have|strong=\"H0376\"coveted|strong=\"H2530\"fields|strong=\"H7704\", and|strong=\"H1004\"taken|strong=\"H5375\"them|strong=\"H5375\"by|strong=\"H1397\"violence, and|strong=\"H1004\"houses|strong=\"H1004\"they|strong=\"H0376\"have|strong=\"H0376\"forcibly taken|strong=\"H5375\"away|strong=\"H5375\": and|strong=\"H1004\"oppressed|strong=\"H6231\"a|strong=\"H5375\"man|strong=\"H0376\"and|strong=\"H1004\"his|strong=\"H5375\"house|strong=\"H1004\", a|strong=\"H5375\"man|strong=\"H0376\"and|strong=\"H1004\"his|strong=\"H5375\"inheritance|strong=\"H5159\".",
      "3": "Therefore|strong=\"H3651\"thus|strong=\"H3541\"saith the|strong=\"H0559\"Lord|strong=\"H3068\": Behold|strong=\"H2005\", I|strong=\"H0834\"devise|strong=\"H2803\"an|strong=\"H8033\"evil|strong=\"H7451\"against|strong=\"H5921\"this|strong=\"H2063\"family|strong=\"H4940\": from|strong=\"H5921\"which|strong=\"H0834\"you|strong=\"H0834\"shall|strong=\"H3068\"not|strong=\"H3808\"withdraw your|strong=\"H3068\"necks|strong=\"H6677\", and|strong=\"H3068\"you|strong=\"H0834\"shall|strong=\"H3068\"not|strong=\"H3808\"walk haughtily|strong=\"H7317\", for|strong=\"H3588\"this|strong=\"H2063\"is|strong=\"H0834\"a|strong=\"H3588\"very|strong=\"H3651\"evil|strong=\"H7451\"time|strong=\"H6256\".",
      "4": "In|strong=\"H5921\"that|strong=\"H3117\"day|strong=\"H3117\"a|strong=\"H5375\"parable|strong=\"H4912\"shall|strong=\"H3117\"be|strong=\"H3117\"taken|strong=\"H5375\"up|strong=\"H5375\"upon|strong=\"H5921\"you|strong=\"H5921\", and|strong=\"H3117\"a|strong=\"H5375\"song shall|strong=\"H3117\"be|strong=\"H3117\"sung with|strong=\"H5921\"melody by|strong=\"H5921\"them|strong=\"H5921\"that|strong=\"H3117\"say|strong=\"H0559\": We|strong=\"H3117\"are|strong=\"H3117\"laid|strong=\"H5375\"waste|strong=\"H7703\"and|strong=\"H3117\"spoiled: the|strong=\"H0559\"portion|strong=\"H2506\"of|strong=\"H3117\"my|strong=\"H5921\"people|strong=\"H5971\"is|strong=\"H1931\"changed|strong=\"H4171\": how|strong=\"H0349\"shall|strong=\"H3117\"he|strong=\"H1931\"depart|strong=\"H4185\"from|strong=\"H5921\"me|strong=\"H5921\", whereas he|strong=\"H1931\"is|strong=\"H1931\"returning that|strong=\"H3117\"will|strong=\"H7704\"divide|strong=\"H2505\"our|strong=\"H5921\"land|strong=\"H7704\"?",
      "5": "Therefore|strong=\"H3651\"thou shalt have|strong=\"H1961\"none|strong=\"H3808\"that|strong=\"H3651\"shall|strong=\"H3068\"cast|strong=\"H7993\"the|strong=\"H3068\"cord|strong=\"H2256\"of|strong=\"H3068\"a|strong=\"H1961\"lot|strong=\"H1486\"in|strong=\"H3068\"the|strong=\"H3068\"assembly|strong=\"H6951\"of|strong=\"H3068\"the|strong=\"H3068\"Lord|strong=\"H3068\".",
      "6": "Speak|strong=\"H5197\"ye not|strong=\"H3808\", saying: It|strong=\"H3808\"shall|strong=\"H3808\"not|strong=\"H3808\"drop upon these|strong=\"H0428\", confusion shall|strong=\"H3808\"not|strong=\"H3808\"take them.",
      "7": "The|strong=\"H0559\"house|strong=\"H1004\"of|strong=\"H1004\"Jacob|strong=\"H3290\"saith: Is|strong=\"H3068\"the|strong=\"H0559\"spirit|strong=\"H7307\"of|strong=\"H1004\"the|strong=\"H0559\"Lord|strong=\"H3068\"straitened, or|strong=\"H0518\"are|strong=\"H0428\"these|strong=\"H0428\"his|strong=\"H3068\"thoughts|strong=\"H1697\"? Are|strong=\"H0428\"not|strong=\"H3808\"my|strong=\"H3068\"words|strong=\"H1697\"good|strong=\"H3190\"to|strong=\"H0559\"him|strong=\"H5973\"that|strong=\"H1697\"walketh uprightly|strong=\"H3477\"?",
      "8": "But|strong=\"H5971\"my|strong=\"H7725\"people|strong=\"H5971\", on|strong=\"H6965\"the|strong=\"H7725\"contrary, are|strong=\"H4421\"risen|strong=\"H6965\"up|strong=\"H6965\"as|strong=\"H6965\"an|strong=\"H6965\"enemy|strong=\"H0341\": you|strong=\"H7725\"have taken|strong=\"H5674\"away|strong=\"H7725\"the|strong=\"H7725\"cloak|strong=\"H8008\"off|strong=\"H6584\"from|strong=\"H7725\"the|strong=\"H7725\"coat: and|strong=\"H6965\"them|strong=\"H7725\"that|strong=\"H7725\"passed|strong=\"H5674\"harmless you|strong=\"H7725\"have turned|strong=\"H7725\"to|strong=\"H7725\"war|strong=\"H4421\".",
      "9": "You|strong=\"H5921\"have|strong=\"H5921\"cast out|strong=\"H1644\"the|strong=\"H5921\"women|strong=\"H0802\"of|strong=\"H1004\"my|strong=\"H5921\"people|strong=\"H5971\"from|strong=\"H5921\"their|strong=\"H3947\"houses|strong=\"H1004\", in|strong=\"H5921\"which|strong=\"H0802\"they|strong=\"H5921\"took|strong=\"H3947\"delight|strong=\"H8588\": you|strong=\"H5921\"have|strong=\"H5921\"taken|strong=\"H3947\"my|strong=\"H5921\"praise|strong=\"H5769\"for|strong=\"H5921\"ever|strong=\"H5769\"from|strong=\"H5921\"their|strong=\"H3947\"children|strong=\"H5768\".",
      "10": "Arise|strong=\"H6965\"ye, and|strong=\"H6965\"depart, for|strong=\"H3588\"there|strong=\"H2063\"is|strong=\"H3808\"no|strong=\"H3808\"rest|strong=\"H4496\"here|strong=\"H2063\"for|strong=\"H3588\"you|strong=\"H3588\". For|strong=\"H3588\"that|strong=\"H3588\"uncleanness of|strong=\"H5668\"the|strong=\"H3588\"land, it|strong=\"H3588\"shall|strong=\"H3808\"be|strong=\"H3808\"corrupted with|strong=\"H6965\"a|strong=\"H3588\"grievous corruption.",
      "11": "Would|strong=\"H3863\"God I|strong=\"H2088\"were|strong=\"H1961\"not|strong=\"H2088\"a|strong=\"H1961\"man|strong=\"H0376\"that|strong=\"H2088\"hath the|strong=\"H1961\"spirit|strong=\"H7307\", and|strong=\"H1980\"that|strong=\"H2088\"I|strong=\"H2088\"rather spoke a|strong=\"H1961\"lie|strong=\"H8267\": I|strong=\"H2088\"will|strong=\"H1961\"let|strong=\"H1980\"drop to|strong=\"H1980\"thee of|strong=\"H0376\"wine|strong=\"H3196\", and|strong=\"H1980\"of|strong=\"H0376\"drunkenness: and|strong=\"H1980\"it|strong=\"H1961\"shall|strong=\"H0376\"be|strong=\"H1961\"this|strong=\"H2088\"people|strong=\"H5971\"upon|strong=\"H1961\"whom it|strong=\"H1961\"shall|strong=\"H0376\"drop.",
      "12": "I|strong=\"H7760\"will|strong=\"H3478\"assemble|strong=\"H0622\"and|strong=\"H3478\"gather|strong=\"H6908\"together|strong=\"H3162\"all|strong=\"H3605\"of|strong=\"H3605\"thee, O Jacob|strong=\"H3290\": I|strong=\"H7760\"will|strong=\"H3478\"bring|strong=\"H7760\"together|strong=\"H3162\"the|strong=\"H3605\"remnant|strong=\"H7611\"of|strong=\"H3605\"Israel|strong=\"H3478\", I|strong=\"H7760\"will|strong=\"H3478\"put|strong=\"H7760\"them|strong=\"H7760\"together|strong=\"H3162\"as|strong=\"H7760\"a|strong=\"H7760\"flock|strong=\"H6629\"in|strong=\"H3478\"the|strong=\"H3605\"fold|strong=\"H1223\", as|strong=\"H7760\"the|strong=\"H3605\"sheep|strong=\"H6629\"in|strong=\"H3478\"the|strong=\"H3605\"midst|strong=\"H8432\"of|strong=\"H3605\"the|strong=\"H3605\"sheepcotes, they|strong=\"H3605\"shall|strong=\"H3478\"make|strong=\"H7760\"a|strong=\"H7760\"tumult by|strong=\"H3478\"reason of|strong=\"H3605\"the|strong=\"H3605\"multitude of|strong=\"H3605\"men|strong=\"H0120\".",
      "13": "For|strong=\"H3068\"he|strong=\"H3068\"shall|strong=\"H3068\"go|strong=\"H3318\"up|strong=\"H5927\"that|strong=\"H3068\"shall|strong=\"H3068\"open|strong=\"H6440\"the|strong=\"H6440\"way|strong=\"H6440\"before|strong=\"H6440\"them|strong=\"H6440\": they|strong=\"H3068\"shall|strong=\"H3068\"divide, and|strong=\"H3068\"pass|strong=\"H5674\"through|strong=\"H5674\"the|strong=\"H6440\"gate|strong=\"H8179\", and|strong=\"H3068\"shall|strong=\"H3068\"come|strong=\"H5927\"in|strong=\"H3068\"by|strong=\"H3068\"it|strong=\"H3068\": and|strong=\"H3068\"their|strong=\"H3068\"king|strong=\"H4428\"shall|strong=\"H3068\"pass|strong=\"H5674\"before|strong=\"H6440\"them|strong=\"H6440\", and|strong=\"H3068\"the|strong=\"H6440\"Lord|strong=\"H3068\"at|strong=\"H3068\"the|strong=\"H6440\"head|strong=\"H7218\"of|strong=\"H4428\"them|strong=\"H6440\"."
    },
    "3": {
      "1": "And|strong=\"H3478\"I|strong=\"H3045\"said|strong=\"H0559\": Hear|strong=\"H8085\", O|strong=\"H4994\"ye princes of|strong=\"H1004\"Jacob|strong=\"H3290\", and|strong=\"H3478\"ye chiefs|strong=\"H7218\"of|strong=\"H1004\"the|strong=\"H0853\"house|strong=\"H1004\"of|strong=\"H1004\"Israel|strong=\"H3478\": Is|strong=\"H4941\"it|strong=\"H3045\"not|strong=\"H3808\"your|strong=\"H8085\"part to|strong=\"H0559\"know|strong=\"H3045\"judgment|strong=\"H4941\",",
      "2": "You|strong=\"H5921\"that|strong=\"H2896\"hate|strong=\"H8130\"good|strong=\"H2896\", and|strong=\"H5785\"love|strong=\"H0157\"evil|strong=\"H7451\": that|strong=\"H2896\"violently pluck off|strong=\"H5921\"their|strong=\"H5921\"skins|strong=\"H5785\"from|strong=\"H5921\"them|strong=\"H5921\", and|strong=\"H5785\"their|strong=\"H5921\"flesh|strong=\"H7607\"from|strong=\"H5921\"their|strong=\"H5921\"bones|strong=\"H6106\"?",
      "3": "Who|strong=\"H0834\"have|strong=\"H0834\"eaten|strong=\"H0398\"the|strong=\"H0853\"flesh|strong=\"H1320\"of|strong=\"H5921\"my|strong=\"H5921\"people|strong=\"H5971\", and|strong=\"H0398\"have|strong=\"H0834\"flayed their|strong=\"H5921\"skin|strong=\"H5785\"from|strong=\"H5921\"off|strong=\"H6584\"them|strong=\"H0853\": and|strong=\"H0398\"have|strong=\"H0834\"broken, and|strong=\"H0398\"chopped their|strong=\"H5921\"bones|strong=\"H6106\"as|strong=\"H0834\"for|strong=\"H5921\"the|strong=\"H0853\"kettle|strong=\"H7037\", and|strong=\"H0398\"as|strong=\"H0834\"flesh|strong=\"H1320\"in|strong=\"H5921\"the|strong=\"H0853\"midst|strong=\"H8432\"of|strong=\"H5921\"the|strong=\"H0853\"pot|strong=\"H5518\".",
      "4": "Then|strong=\"H0227\"shall|strong=\"H3068\"they|strong=\"H1992\"cry|strong=\"H2199\"to|strong=\"H0413\"the|strong=\"H0853\"Lord|strong=\"H3068\", and|strong=\"H3068\"he|strong=\"H0834\"will|strong=\"H3068\"not|strong=\"H3808\"hear them|strong=\"H0413\": and|strong=\"H3068\"he|strong=\"H0834\"will|strong=\"H3068\"hide|strong=\"H5641\"his|strong=\"H3068\"face|strong=\"H6440\"from|strong=\"H6440\"them|strong=\"H0413\"at|strong=\"H0413\"that|strong=\"H0834\"time|strong=\"H6256\", as|strong=\"H0834\"they|strong=\"H1992\"have|strong=\"H0834\"behaved wickedly in|strong=\"H0413\"their|strong=\"H3068\"devices.",
      "5": "Thus|strong=\"H3541\"saith the|strong=\"H0853\"Lord|strong=\"H3068\"concerning|strong=\"H5921\"the|strong=\"H0853\"prophets|strong=\"H5030\"that|strong=\"H0834\"make|strong=\"H5414\"my|strong=\"H5414\"people|strong=\"H5971\"err|strong=\"H8582\": that|strong=\"H0834\"bite with|strong=\"H3068\"their|strong=\"H3068\"teeth|strong=\"H8127\", and|strong=\"H3068\"preach peace|strong=\"H7965\": and|strong=\"H3068\"if|strong=\"H0834\"a|strong=\"H5414\"man give|strong=\"H5414\"not|strong=\"H3808\"something into|strong=\"H5921\"their|strong=\"H3068\"mouth|strong=\"H6310\", they|strong=\"H0834\"prepare|strong=\"H6942\"war|strong=\"H4421\"against|strong=\"H5921\"him|strong=\"H5414\".",
      "6": "Therefore|strong=\"H3651\"night|strong=\"H3915\"shall|strong=\"H3117\"be|strong=\"H3117\"to|strong=\"H0935\"you|strong=\"H5921\"instead of|strong=\"H3117\"vision|strong=\"H2377\", and|strong=\"H0935\"darkness|strong=\"H2821\"to|strong=\"H0935\"you|strong=\"H5921\"instead of|strong=\"H3117\"divination|strong=\"H7080\"; and|strong=\"H0935\"the|strong=\"H5921\"sun|strong=\"H8121\"shall|strong=\"H3117\"go|strong=\"H0935\"down|strong=\"H5921\"upon|strong=\"H5921\"the|strong=\"H5921\"prophets|strong=\"H5030\", and|strong=\"H0935\"the|strong=\"H5921\"day|strong=\"H3117\"shall|strong=\"H3117\"be|strong=\"H3117\"darkened|strong=\"H2821\"over|strong=\"H5921\"them|strong=\"H5921\".",
      "7": "And|strong=\"H0430\"they|strong=\"H3588\"shall|strong=\"H0369\"be|strong=\"H0430\"confounded|strong=\"H2659\"that|strong=\"H3588\"see visions|strong=\"H7080\", and|strong=\"H0430\"the|strong=\"H3605\"diviners|strong=\"H7080\"shall|strong=\"H0369\"be|strong=\"H0430\"confounded|strong=\"H2659\": and|strong=\"H0430\"they|strong=\"H3588\"shall|strong=\"H0369\"all|strong=\"H3605\"cover|strong=\"H5844\"their|strong=\"H3605\"faces, because|strong=\"H3588\"there|strong=\"H0369\"is|strong=\"H0369\"no|strong=\"H0369\"answer|strong=\"H4617\"of|strong=\"H0430\"God|strong=\"H0430\".",
      "8": "But|strong=\"H0199\"yet|strong=\"H3068\"I|strong=\"H0595\"am|strong=\"H0595\"filled|strong=\"H4390\"with|strong=\"H4390\"the|strong=\"H0853\"strength|strong=\"H1369\"of|strong=\"H3068\"the|strong=\"H0853\"spirit|strong=\"H7307\"of|strong=\"H3068\"the|strong=\"H0853\"Lord|strong=\"H3068\", with|strong=\"H4390\"judgment|strong=\"H4941\", and|strong=\"H3068\"power|strong=\"H1369\": to|strong=\"H3068\"declare|strong=\"H5046\"unto Jacob|strong=\"H3290\"his|strong=\"H3068\"wickedness, and|strong=\"H3068\"to|strong=\"H3068\"Israel|strong=\"H3478\"his|strong=\"H3068\"sin|strong=\"H2403\".",
      "9": "Hear|strong=\"H8085\"this|strong=\"H2063\", ye princes of|strong=\"H1004\"the|strong=\"H3605\"house|strong=\"H1004\"of|strong=\"H1004\"Jacob|strong=\"H3290\", and|strong=\"H3478\"ye judges of|strong=\"H1004\"the|strong=\"H3605\"house|strong=\"H1004\"of|strong=\"H1004\"Israel|strong=\"H3478\": you|strong=\"H3605\"that|strong=\"H3605\"abhor|strong=\"H8581\"judgment|strong=\"H4941\", and|strong=\"H3478\"pervert all|strong=\"H3605\"that|strong=\"H3605\"is|strong=\"H3605\"right|strong=\"H3477\".",
      "10": "You|strong=\"H6726\"that|strong=\"H3389\"build|strong=\"H1129\"up|strong=\"H1129\"Sion with|strong=\"H3389\"blood|strong=\"H1818\", and|strong=\"H3389\"Jerusalem|strong=\"H3389\"with|strong=\"H3389\"iniquity|strong=\"H5766\".",
      "11": "Her|strong=\"H5921\"princes have|strong=\"H5030\"judged|strong=\"H8199\"for|strong=\"H5921\"bribes|strong=\"H7810\", and|strong=\"H0935\"her|strong=\"H5921\"priests|strong=\"H3548\"have|strong=\"H5030\"taught|strong=\"H3384\"for|strong=\"H5921\"hire, and|strong=\"H0935\"her|strong=\"H5921\"prophets|strong=\"H5030\"divined for|strong=\"H5921\"money|strong=\"H3701\": and|strong=\"H0935\"they|strong=\"H5921\"leaned|strong=\"H8172\"upon|strong=\"H5921\"the|strong=\"H0559\"Lord|strong=\"H3068\", saying|strong=\"H0559\": Is|strong=\"H3068\"not|strong=\"H3808\"the|strong=\"H0559\"Lord|strong=\"H3068\"in|strong=\"H5921\"the|strong=\"H0559\"midst|strong=\"H7130\"of|strong=\"H3068\"us|strong=\"H5921\"? no|strong=\"H3808\"evil|strong=\"H7451\"shall|strong=\"H3548\"come|strong=\"H0935\"upon|strong=\"H5921\"us|strong=\"H5921\".",
      "12": "Therefore|strong=\"H3651\", because|strong=\"H3651\"of|strong=\"H1004\"you|strong=\"H3651\", Sion shall|strong=\"H1004\"be|strong=\"H1961\"ploughed as|strong=\"H1961\"a|strong=\"H1961\"field|strong=\"H7704\", and|strong=\"H1004\"Jerusalem|strong=\"H3389\"shall|strong=\"H1004\"be|strong=\"H1961\"as|strong=\"H1961\"a|strong=\"H1961\"heap|strong=\"H5856\"of|strong=\"H1004\"stones, and|strong=\"H1004\"the|strong=\"H1961\"mountain|strong=\"H2022\"of|strong=\"H1004\"the|strong=\"H1961\"temple|strong=\"H1004\"as|strong=\"H1961\"the|strong=\"H1961\"high|strong=\"H1116\"places|strong=\"H1116\"of|strong=\"H1004\"the|strong=\"H1961\"forests."
    },
    "4": {
      "1": "And|strong=\"H3068\"it|strong=\"H1931\"shall|strong=\"H3068\"come|strong=\"H1961\"to|strong=\"H1961\"pass|strong=\"H1961\"in|strong=\"H5921\"the|strong=\"H5921\"last|strong=\"H0319\"days|strong=\"H3117\", that|strong=\"H3117\"the|strong=\"H5921\"mountain|strong=\"H2022\"of|strong=\"H1004\"the|strong=\"H5921\"house|strong=\"H1004\"of|strong=\"H1004\"the|strong=\"H5921\"Lord|strong=\"H3068\"shall|strong=\"H3068\"be|strong=\"H1961\"prepared|strong=\"H3559\"in|strong=\"H5921\"the|strong=\"H5921\"top|strong=\"H7218\"of|strong=\"H1004\"mountains|strong=\"H2022\", and|strong=\"H3068\"high|strong=\"H5375\"above|strong=\"H5921\"the|strong=\"H5921\"hills|strong=\"H1389\": and|strong=\"H3068\"people|strong=\"H5971\"shall|strong=\"H3068\"flow to|strong=\"H1961\"it|strong=\"H1931\".",
      "2": "And|strong=\"H1980\"many|strong=\"H7227\"nations|strong=\"H1471\"shall|strong=\"H3068\"come|strong=\"H1980\"in|strong=\"H1980\"haste, and|strong=\"H1980\"say|strong=\"H0559\": Come|strong=\"H1980\", let|strong=\"H1980\"us|strong=\"H0413\"go|strong=\"H1980\"up|strong=\"H5927\"to|strong=\"H0413\"the|strong=\"H0559\"mountain|strong=\"H2022\"of|strong=\"H1004\"the|strong=\"H0559\"Lord|strong=\"H3068\", and|strong=\"H1980\"to|strong=\"H0413\"the|strong=\"H0559\"house|strong=\"H1004\"of|strong=\"H1004\"the|strong=\"H0559\"God|strong=\"H0430\"of|strong=\"H1004\"Jacob|strong=\"H3290\": and|strong=\"H1980\"he|strong=\"H3588\"will|strong=\"H3068\"teach|strong=\"H3384\"us|strong=\"H0413\"of|strong=\"H1004\"his|strong=\"H3068\"ways|strong=\"H1870\", and|strong=\"H1980\"we|strong=\"H3588\"will|strong=\"H3068\"walk|strong=\"H1980\"in|strong=\"H1980\"his|strong=\"H3068\"paths|strong=\"H0734\": for|strong=\"H3588\"the|strong=\"H0559\"law|strong=\"H8451\"shall|strong=\"H3068\"go|strong=\"H1980\"forth|strong=\"H3318\"out|strong=\"H3318\"of|strong=\"H1004\"Sion, and|strong=\"H1980\"the|strong=\"H0559\"word|strong=\"H1697\"of|strong=\"H1004\"the|strong=\"H0559\"Lord|strong=\"H3068\"out|strong=\"H3318\"of|strong=\"H1004\"Jerusalem|strong=\"H3389\".",
      "3": "And|strong=\"H2719\"he|strong=\"H5704\"shall|strong=\"H3808\"judge|strong=\"H8199\"among|strong=\"H0996\"many|strong=\"H7227\"people|strong=\"H5971\", and|strong=\"H2719\"rebuke|strong=\"H3198\"strong|strong=\"H6099\"nations|strong=\"H1471\"afar|strong=\"H7350\"off|strong=\"H7350\": and|strong=\"H2719\"they|strong=\"H3808\"shall|strong=\"H3808\"beat|strong=\"H3807\"their|strong=\"H5375\"swords|strong=\"H2719\"into|strong=\"H0413\"ploughshares, and|strong=\"H2719\"their|strong=\"H5375\"spears|strong=\"H2595\"into|strong=\"H0413\"spades: nation|strong=\"H1471\"shall|strong=\"H3808\"not|strong=\"H3808\"take|strong=\"H5375\"sword|strong=\"H2719\"against|strong=\"H0413\"nation|strong=\"H1471\": neither|strong=\"H3808\"shall|strong=\"H3808\"they|strong=\"H3808\"learn|strong=\"H3925\"war|strong=\"H4421\"any|strong=\"H5750\"more|strong=\"H5750\".",
      "4": "And|strong=\"H3068\"every|strong=\"H0376\"man|strong=\"H0376\"shall|strong=\"H3068\"sit|strong=\"H3427\"under|strong=\"H8478\"his|strong=\"H3068\"vine|strong=\"H1612\", and|strong=\"H3068\"under|strong=\"H8478\"his|strong=\"H3068\"fig|strong=\"H8384\"tree|strong=\"H8384\", and|strong=\"H3068\"there|strong=\"H0369\"shall|strong=\"H3068\"be|strong=\"H0376\"none|strong=\"H0369\"to|strong=\"H1696\"make|strong=\"H2729\"them|strong=\"H8478\"afraid|strong=\"H2729\": for|strong=\"H3588\"the|strong=\"H3588\"mouth|strong=\"H6310\"of|strong=\"H0376\"the|strong=\"H3588\"Lord|strong=\"H3068\"of|strong=\"H0376\"hosts|strong=\"H6635\"hath spoken|strong=\"H1696\".",
      "5": "For|strong=\"H3588\"all|strong=\"H3605\"people|strong=\"H5971\"will|strong=\"H3068\"walk every|strong=\"H3605\"one|strong=\"H0376\"in|strong=\"H0430\"the|strong=\"H3605\"name|strong=\"H8034\"of|strong=\"H0376\"his|strong=\"H3605\"god|strong=\"H0430\": but|strong=\"H3588\"we|strong=\"H0587\"will|strong=\"H3068\"walk in|strong=\"H0430\"the|strong=\"H3605\"name|strong=\"H8034\"of|strong=\"H0376\"the|strong=\"H3605\"Lord|strong=\"H3068\"our|strong=\"H3068\"God|strong=\"H0430\"for|strong=\"H3588\"ever|strong=\"H5703\"and|strong=\"H3068\"ever|strong=\"H5703\".",
      "6": "In|strong=\"H3068\"that|strong=\"H0834\"day|strong=\"H3117\", saith the|strong=\"H0834\"Lord|strong=\"H3068\", I|strong=\"H0834\"will|strong=\"H3068\"gather|strong=\"H6908\"up her|strong=\"H3117\"that|strong=\"H0834\"halteth: and|strong=\"H3068\"her|strong=\"H3117\"that|strong=\"H0834\"I|strong=\"H0834\"had|strong=\"H3068\"cast|strong=\"H5080\"out|strong=\"H5080\", I|strong=\"H0834\"will|strong=\"H3068\"gather|strong=\"H6908\"up: and|strong=\"H3068\"her|strong=\"H3117\"whom|strong=\"H0834\"I|strong=\"H0834\"had|strong=\"H3068\"afflicted.",
      "7": "And|strong=\"H3068\"I|strong=\"H5704\"will|strong=\"H3068\"make|strong=\"H7760\"her|strong=\"H5921\"that|strong=\"H3068\"halted, a|strong=\"H7760\"remnant|strong=\"H7611\": and|strong=\"H3068\"her|strong=\"H5921\"that|strong=\"H3068\"hath been|strong=\"H5769\"afflicted|strong=\"H5921\", a|strong=\"H7760\"mighty|strong=\"H6099\"nation|strong=\"H1471\": and|strong=\"H3068\"the|strong=\"H0853\"Lord|strong=\"H3068\"will|strong=\"H3068\"reign|strong=\"H4427\"over|strong=\"H5921\"them|strong=\"H0853\"in|strong=\"H5921\"mount|strong=\"H2022\"Sion, from|strong=\"H5921\"this|strong=\"H6258\"time|strong=\"H6258\"now|strong=\"H6258\"and|strong=\"H3068\"for|strong=\"H5921\"ever|strong=\"H5769\".",
      "8": "And|strong=\"H0935\"thou, O|strong=\"H0859\"cloudy tower|strong=\"H4026\"of|strong=\"H1323\"the|strong=\"H0935\"flock|strong=\"H5739\", of|strong=\"H1323\"the|strong=\"H0935\"daughter|strong=\"H1323\"of|strong=\"H1323\"Sion, unto thee shall|strong=\"H4467\"it|strong=\"H5704\"come|strong=\"H0935\": yea the|strong=\"H0935\"first|strong=\"H7223\"power shall|strong=\"H4467\"come|strong=\"H0935\", the|strong=\"H0935\"kingdom|strong=\"H4467\"to|strong=\"H0935\"the|strong=\"H0935\"daughter|strong=\"H1323\"of|strong=\"H1323\"Jerusalem|strong=\"H3389\".",
      "9": "Now|strong=\"H6258\", why|strong=\"H4100\"art thou drawn together|strong=\"H2388\"with|strong=\"H4428\"grief? Hast thou no|strong=\"H0369\"king|strong=\"H4428\"in|strong=\"H4428\"thee, or|strong=\"H0518\"is|strong=\"H0369\"thy counsellor perished|strong=\"H0006\", because|strong=\"H3588\"sorrow hath taken|strong=\"H2388\"thee as|strong=\"H3588\"a|strong=\"H3588\"woman in|strong=\"H4428\"labour?",
      "10": "Be|strong=\"H3068\"in|strong=\"H0935\"pain and|strong=\"H0935\"labour, O|strong=\"H3068\"daughter|strong=\"H1323\"of|strong=\"H3068\"Sion, as|strong=\"H5704\"a|strong=\"H3588\"woman|strong=\"H1323\"that|strong=\"H3588\"bringeth forth|strong=\"H3318\": for|strong=\"H3588\"now|strong=\"H6258\"shalt thou go|strong=\"H3318\"out|strong=\"H3318\"of|strong=\"H3068\"the|strong=\"H3588\"city|strong=\"H7151\", and|strong=\"H0935\"shalt dwell|strong=\"H7931\"in|strong=\"H0935\"the|strong=\"H3588\"country|strong=\"H7704\", and|strong=\"H0935\"shalt come|strong=\"H0935\"even|strong=\"H5704\"to|strong=\"H0935\"Babylon|strong=\"H0894\", there|strong=\"H8033\"thou shalt be|strong=\"H3068\"delivered|strong=\"H5337\": there|strong=\"H8033\"the|strong=\"H3588\"Lord|strong=\"H3068\"will|strong=\"H3068\"redeem|strong=\"H1350\"thee out|strong=\"H3318\"of|strong=\"H3068\"the|strong=\"H3588\"hand|strong=\"H3709\"of|strong=\"H3068\"thy enemies|strong=\"H0341\".",
      "11": "And|strong=\"H5869\"now|strong=\"H6258\"many|strong=\"H7227\"nations|strong=\"H1471\"are|strong=\"H5869\"gathered|strong=\"H0622\"together|strong=\"H0622\"against|strong=\"H5921\"thee, and|strong=\"H5869\"they|strong=\"H5921\"say|strong=\"H0559\": Let|strong=\"H6258\"her|strong=\"H5921\"be|strong=\"H1471\"stoned: and|strong=\"H5869\"let|strong=\"H6258\"our|strong=\"H5921\"eye|strong=\"H5869\"look|strong=\"H5869\"upon|strong=\"H5921\"Sion.",
      "12": "But|strong=\"H3588\"they|strong=\"H1992\"have|strong=\"H3045\"not|strong=\"H3808\"known|strong=\"H3045\"the|strong=\"H3588\"thoughts|strong=\"H4284\"of|strong=\"H3068\"the|strong=\"H3588\"Lord|strong=\"H3068\", and|strong=\"H3068\"have|strong=\"H3045\"not|strong=\"H3808\"understood|strong=\"H0995\"his|strong=\"H3068\"counsel|strong=\"H6098\": because|strong=\"H3588\"he|strong=\"H3588\"hath gathered|strong=\"H6908\"them|strong=\"H1992\"together|strong=\"H6908\"as|strong=\"H3068\"the|strong=\"H3588\"hay of|strong=\"H3068\"the|strong=\"H3588\"floor|strong=\"H1637\".",
      "13": "Arise|strong=\"H6965\", and|strong=\"H6965\"tread, O|strong=\"H3068\"daughter|strong=\"H1323\"of|strong=\"H0776\"Sion: for|strong=\"H3588\"I|strong=\"H3588\"will|strong=\"H3068\"make|strong=\"H7760\"thy horn|strong=\"H7161\"iron|strong=\"H1270\", and|strong=\"H6965\"thy hoofs|strong=\"H6541\"I|strong=\"H3588\"will|strong=\"H3068\"make|strong=\"H7760\"brass: and|strong=\"H6965\"thou shalt beat in|strong=\"H3068\"pieces many|strong=\"H7227\"peoples|strong=\"H5971\", and|strong=\"H6965\"shalt immolate the|strong=\"H3605\"spoils of|strong=\"H0776\"them|strong=\"H7760\"to|strong=\"H3068\"the|strong=\"H3605\"Lord|strong=\"H3068\", and|strong=\"H6965\"their|strong=\"H3605\"strength|strong=\"H2428\"to|strong=\"H3068\"the|strong=\"H3605\"Lord|strong=\"H3068\"of|strong=\"H0776\"the|strong=\"H3605\"whole|strong=\"H3605\"earth|strong=\"H0776\"."
    },
    "5": {
      "1": "Now|strong=\"H1961\"shalt thou be|strong=\"H1961\"laid|strong=\"H3318\"waste, O|strong=\"H0859\"daughter of|strong=\"H3117\"the|strong=\"H4480\"robber: they|strong=\"H3117\"have|strong=\"H1961\"laid|strong=\"H3318\"siege against|strong=\"H4480\"us|strong=\"H3117\", with|strong=\"H3117\"a|strong=\"H1961\"rod shall|strong=\"H3478\"they|strong=\"H3117\"strike the|strong=\"H4480\"cheek of|strong=\"H3117\"the|strong=\"H4480\"judge of|strong=\"H3117\"Israel|strong=\"H3478\".",
      "2": "AND|strong=\"H1121\"THOU, BETHLEHEM Ephrata, art a|strong=\"H5414\"little one|strong=\"H1121\"among|strong=\"H5921\"the|strong=\"H5921\"thousands of|strong=\"H1121\"Juda: out|strong=\"H5921\"of|strong=\"H1121\"thee shall|strong=\"H1121\"he|strong=\"H5704\"come|strong=\"H7725\"forth|strong=\"H3205\"unto me|strong=\"H5414\"that|strong=\"H3651\"is|strong=\"H3651\"to|strong=\"H5704\"be|strong=\"H1121\"the|strong=\"H5921\"ruler in|strong=\"H5921\"Israel|strong=\"H3478\": and|strong=\"H1121\"his|strong=\"H5414\"going|strong=\"H7725\"forth|strong=\"H3205\"is|strong=\"H3651\"from|strong=\"H7725\"the|strong=\"H5921\"beginning|strong=\"H5704\", from|strong=\"H7725\"the|strong=\"H5921\"days of|strong=\"H1121\"eternity.",
      "3": "Therefore|strong=\"H6258\"will|strong=\"H3068\"he|strong=\"H3588\"give them|strong=\"H5975\"up|strong=\"H5975\"even|strong=\"H5704\"till|strong=\"H5704\"the|strong=\"H3588\"time|strong=\"H6258\"wherein she|strong=\"H3588\"that|strong=\"H3588\"travaileth shall|strong=\"H3068\"bring|strong=\"H1431\"forth: and|strong=\"H3068\"the|strong=\"H3588\"remnant of|strong=\"H0776\"his|strong=\"H3068\"brethren shall|strong=\"H3068\"be|strong=\"H8034\"converted to|strong=\"H5704\"the|strong=\"H3588\"children of|strong=\"H0776\"Israel.",
      "4": "And|strong=\"H0935\"he|strong=\"H3588\"shall|strong=\"H0776\"stand|strong=\"H6965\", and|strong=\"H0935\"feed|strong=\"H7462\"in|strong=\"H5921\"the|strong=\"H5921\"strength of|strong=\"H0776\"the|strong=\"H5921\"Lord, in|strong=\"H5921\"the|strong=\"H5921\"height of|strong=\"H0776\"the|strong=\"H5921\"name of|strong=\"H0776\"the|strong=\"H5921\"Lord his|strong=\"H5921\"God: and|strong=\"H0935\"they|strong=\"H3588\"shall|strong=\"H0776\"be|strong=\"H1961\"converted, for|strong=\"H3588\"now|strong=\"H1961\"shall|strong=\"H0776\"he|strong=\"H3588\"be|strong=\"H1961\"magnified even|strong=\"H3588\"to|strong=\"H0935\"the|strong=\"H5921\"ends of|strong=\"H0776\"the|strong=\"H5921\"earth|strong=\"H0776\".",
      "5": "And|strong=\"H0935\"this|strong=\"H3588\"man shall|strong=\"H0776\"be|strong=\"H0776\"our|strong=\"H3588\"peace, when|strong=\"H3588\"the|strong=\"H0853\"Assyrian shall|strong=\"H0776\"come|strong=\"H0935\"into|strong=\"H0935\"our|strong=\"H3588\"land|strong=\"H0776\", and|strong=\"H0935\"when|strong=\"H3588\"he|strong=\"H3588\"shall|strong=\"H0776\"set|strong=\"H0935\"his|strong=\"H0935\"foot|strong=\"H1869\"in|strong=\"H0935\"our|strong=\"H3588\"houses: and|strong=\"H0935\"we|strong=\"H3588\"shall|strong=\"H0776\"raise against|strong=\"H0935\"him|strong=\"H0853\"seven shepherds|strong=\"H7462\", and|strong=\"H0935\"eight principal men.",
      "6": "And|strong=\"H1121\"they|strong=\"H0834\"shall|strong=\"H1121\"feed the|strong=\"H0853\"land|strong=\"H7130\"of|strong=\"H1121\"Assyria with|strong=\"H3068\"the|strong=\"H0853\"sword, and|strong=\"H1121\"the|strong=\"H0853\"land|strong=\"H7130\"of|strong=\"H1121\"Nemrod with|strong=\"H3068\"the|strong=\"H0853\"spears thereof: and|strong=\"H1121\"he|strong=\"H0834\"shall|strong=\"H1121\"deliver us|strong=\"H5921\"from|strong=\"H5921\"the|strong=\"H0853\"Assyrian, when|strong=\"H1961\"he|strong=\"H0834\"shall|strong=\"H1121\"come|strong=\"H1961\"into|strong=\"H5921\"our|strong=\"H3068\"land|strong=\"H7130\", and|strong=\"H1121\"when|strong=\"H1961\"he|strong=\"H0834\"shall|strong=\"H1121\"tread in|strong=\"H5921\"our|strong=\"H3068\"borders.",
      "7": "And|strong=\"H6629\"the|strong=\"H0834\"remnant|strong=\"H7611\"of|strong=\"H7611\"Jacob|strong=\"H3290\"shall|strong=\"H0929\"be|strong=\"H1961\"in|strong=\"H7130\"the|strong=\"H0834\"midst|strong=\"H7130\"of|strong=\"H7611\"many|strong=\"H7227\"peoples|strong=\"H5971\"as|strong=\"H0834\"a|strong=\"H1961\"dew from|strong=\"H1961\"the|strong=\"H0834\"Lord, and|strong=\"H6629\"as|strong=\"H0834\"drops upon|strong=\"H1961\"the|strong=\"H0834\"grass, which|strong=\"H0834\"waiteth not|strong=\"H0369\"for|strong=\"H0518\"man|strong=\"H0369\", nor|strong=\"H0369\"tarrieth for|strong=\"H0518\"the|strong=\"H0834\"children of|strong=\"H7611\"men|strong=\"H5971\".",
      "8": "And|strong=\"H3027\"the|strong=\"H3605\"remnant of|strong=\"H3027\"Jacob shall|strong=\"H3027\"be|strong=\"H3027\"among|strong=\"H5921\"the|strong=\"H3605\"Gentiles in|strong=\"H5921\"the|strong=\"H3605\"midst of|strong=\"H3027\"many peoples as|strong=\"H3027\"a|strong=\"H3772\"lion among|strong=\"H5921\"the|strong=\"H3605\"beasts of|strong=\"H3027\"the|strong=\"H3605\"forests, and|strong=\"H3027\"as|strong=\"H3027\"a|strong=\"H3772\"young lion among|strong=\"H5921\"the|strong=\"H3605\"flocks of|strong=\"H3027\"sheep: who|strong=\"H3605\"when|strong=\"H5921\"he|strong=\"H5921\"shall|strong=\"H3027\"go through|strong=\"H3027\"and|strong=\"H3027\"tread down|strong=\"H3772\", and|strong=\"H3027\"take|strong=\"H7311\", there|strong=\"H3605\"is|strong=\"H3027\"none|strong=\"H3605\"to|strong=\"H5921\"deliver.",
      "9": "Thy hand shall|strong=\"H3068\"be|strong=\"H1961\"lifted up|strong=\"H1961\"over|strong=\"H3068\"thy enemies, and|strong=\"H3068\"all|strong=\"H3117\"thy enemies shall|strong=\"H3068\"be|strong=\"H1961\"cut|strong=\"H3772\"off|strong=\"H3772\".",
      "10": "And|strong=\"H0776\"it|strong=\"H3772\"shall|strong=\"H0776\"come to|strong=\"H0776\"pass in|strong=\"H0776\"that|strong=\"H3605\"day, saith the|strong=\"H3605\"Lord, that|strong=\"H3605\"I|strong=\"H0776\"will|strong=\"H0776\"take away|strong=\"H3605\"thy horses out|strong=\"H3605\"of|strong=\"H0776\"the|strong=\"H3605\"midst of|strong=\"H0776\"thee, and|strong=\"H0776\"will|strong=\"H0776\"destroy|strong=\"H3605\"thy chariots.",
      "11": "And|strong=\"H3027\"I|strong=\"H3808\"will|strong=\"H1961\"destroy|strong=\"H3772\"the|strong=\"H1961\"cities of|strong=\"H3027\"thy land, and|strong=\"H3027\"will|strong=\"H1961\"throw down|strong=\"H3772\"all thy strong holds, and|strong=\"H3027\"I|strong=\"H3808\"will|strong=\"H1961\"take|strong=\"H1961\"away sorceries|strong=\"H3785\"out|strong=\"H3027\"of|strong=\"H3027\"thy hand|strong=\"H3027\", and|strong=\"H3027\"there|strong=\"H1961\"shall|strong=\"H3808\"be|strong=\"H1961\"no|strong=\"H3808\"divinations in|strong=\"H1961\"thee.",
      "12": "And|strong=\"H3027\"I|strong=\"H3808\"will|strong=\"H3027\"destroy|strong=\"H3772\"thy graven|strong=\"H6456\"things|strong=\"H4639\", and|strong=\"H3027\"thy statues out|strong=\"H3027\"of|strong=\"H3027\"the|strong=\"H3772\"midst|strong=\"H7130\"of|strong=\"H3027\"thee: and|strong=\"H3027\"thou shalt no|strong=\"H3808\"more|strong=\"H5750\"adore the|strong=\"H3772\"works|strong=\"H4639\"of|strong=\"H3027\"thy hands|strong=\"H3027\".",
      "13": "And|strong=\"H0842\"I will pluck|strong=\"H5428\"up thy groves out of|strong=\"H7130\"the|strong=\"H7130\"midst|strong=\"H7130\"of|strong=\"H7130\"thee: and|strong=\"H0842\"will crush thy cities|strong=\"H5892\".",
      "14": "And|strong=\"H8085\"I|strong=\"H0834\"will|strong=\"H0834\"execute vengeance|strong=\"H5359\"in|strong=\"H8085\"wrath|strong=\"H2534\"and|strong=\"H8085\"in|strong=\"H8085\"indignation among|strong=\"H0854\"all the|strong=\"H0834\"nations|strong=\"H1471\"that|strong=\"H0834\"have|strong=\"H0834\"not|strong=\"H3808\"given|strong=\"H8085\"ear."
    },
    "6": {
      "1": "Hear|strong=\"H8085\"ye what|strong=\"H0834\"the|strong=\"H0853\"Lord|strong=\"H3068\"saith: Arise|strong=\"H6965\", contend|strong=\"H7378\"thou in|strong=\"H3068\"judgment|strong=\"H0834\"against|strong=\"H0854\"the|strong=\"H0853\"mountains|strong=\"H2022\", and|strong=\"H6965\"let|strong=\"H4994\"the|strong=\"H0853\"hills|strong=\"H1389\"hear|strong=\"H8085\"thy voice|strong=\"H6963\".",
      "2": "Let the|strong=\"H0853\"mountains|strong=\"H2022\"hear|strong=\"H8085\"the|strong=\"H0853\"judgment|strong=\"H3198\"of|strong=\"H0776\"the|strong=\"H0853\"Lord|strong=\"H3068\", and|strong=\"H3068\"the|strong=\"H0853\"strong foundations|strong=\"H4146\"of|strong=\"H0776\"the|strong=\"H0853\"earth|strong=\"H0776\": for|strong=\"H3588\"the|strong=\"H0853\"Lord|strong=\"H3068\"will|strong=\"H3068\"enter into|strong=\"H0776\"judgment|strong=\"H3198\"with|strong=\"H5973\"his|strong=\"H3068\"people|strong=\"H5971\", and|strong=\"H3068\"he|strong=\"H3588\"will|strong=\"H3068\"plead|strong=\"H3198\"against|strong=\"H5973\"Israel|strong=\"H3478\".",
      "3": "O|strong=\"H4100\"my|strong=\"H4100\"people|strong=\"H5971\", what|strong=\"H4100\"have I|strong=\"H4100\"done|strong=\"H6213\"to|strong=\"H4100\"thee, or|strong=\"H6213\"in|strong=\"H3811\"what|strong=\"H4100\"have I|strong=\"H4100\"molested thee? answer|strong=\"H6030\"thou me|strong=\"H4100\".",
      "4": "For|strong=\"H3588\"I|strong=\"H3588\"brought|strong=\"H5927\"thee up|strong=\"H5927\"out|strong=\"H7971\"of|strong=\"H0776\"the|strong=\"H0853\"land|strong=\"H0776\"of|strong=\"H0776\"Egypt|strong=\"H4714\", and|strong=\"H4872\"delivered|strong=\"H5927\"thee out|strong=\"H7971\"of|strong=\"H0776\"the|strong=\"H0853\"house|strong=\"H1004\"of|strong=\"H0776\"slaves|strong=\"H5650\": and|strong=\"H4872\"I|strong=\"H3588\"sent|strong=\"H7971\"before|strong=\"H6440\"thy face|strong=\"H6440\"Moses|strong=\"H4872\", and|strong=\"H4872\"Aaron|strong=\"H0175\", and|strong=\"H4872\"Mary.",
      "5": "O|strong=\"H4994\"my|strong=\"H3068\"people|strong=\"H5971\", remember|strong=\"H2142\", I|strong=\"H5704\"pray|strong=\"H4994\"thee, what|strong=\"H4100\"Balach the|strong=\"H0853\"king|strong=\"H4428\"of|strong=\"H1121\"Moab|strong=\"H4124\"purposed|strong=\"H3289\": and|strong=\"H1121\"what|strong=\"H4100\"Balaam|strong=\"H1109\"the|strong=\"H0853\"son|strong=\"H1121\"of|strong=\"H1121\"Beor|strong=\"H1160\"answered|strong=\"H6030\"him|strong=\"H0853\", from|strong=\"H4480\"Setim to|strong=\"H5704\"Galgal, that|strong=\"H3045\"thou mightest know|strong=\"H3045\"the|strong=\"H0853\"justices of|strong=\"H1121\"the|strong=\"H0853\"Lord|strong=\"H3068\".",
      "6": "What|strong=\"H4100\"shall|strong=\"H1121\"I|strong=\"H8141\"offer to|strong=\"H3068\"the|strong=\"H3068\"Lord|strong=\"H3068\"that|strong=\"H3068\"is|strong=\"H3068\"worthy? wherewith shall|strong=\"H1121\"I|strong=\"H8141\"kneel before|strong=\"H6923\"the|strong=\"H3068\"high|strong=\"H4791\"God|strong=\"H0430\"? shall|strong=\"H1121\"I|strong=\"H8141\"offer holocausts unto him|strong=\"H0430\", and|strong=\"H1121\"calves|strong=\"H5695\"of|strong=\"H1121\"a|strong=\"H3068\"year|strong=\"H8141\"old|strong=\"H1121\"?",
      "7": "May|strong=\"H3068\"the|strong=\"H5414\"Lord|strong=\"H3068\"be|strong=\"H3068\"appeased with|strong=\"H3068\"thousands|strong=\"H0505\"of|strong=\"H3068\"rams|strong=\"H0352\", or|strong=\"H3068\"with|strong=\"H3068\"many thousands|strong=\"H0505\"of|strong=\"H3068\"fat he|strong=\"H3068\"goats? shall|strong=\"H3068\"I|strong=\"H5414\"give|strong=\"H5414\"my|strong=\"H5414\"firstborn|strong=\"H1060\"for|strong=\"H3068\"my|strong=\"H5414\"wickedness, the|strong=\"H5414\"fruit|strong=\"H6529\"of|strong=\"H3068\"my|strong=\"H5414\"body|strong=\"H0990\"for|strong=\"H3068\"the|strong=\"H5414\"sin|strong=\"H2403\"of|strong=\"H3068\"my|strong=\"H5414\"soul|strong=\"H5315\"?",
      "8": "I|strong=\"H3588\"will|strong=\"H3068\"shew thee, O|strong=\"H3068\"man|strong=\"H0120\", what|strong=\"H4100\"is|strong=\"H3068\"good|strong=\"H2896\", and|strong=\"H3068\"what|strong=\"H4100\"the|strong=\"H3588\"Lord|strong=\"H3068\"requireth of|strong=\"H0430\"thee: Verily, to|strong=\"H3068\"do|strong=\"H6213\"judgment|strong=\"H4941\", and|strong=\"H3068\"to|strong=\"H3068\"love|strong=\"H0160\"mercy|strong=\"H3068\", and|strong=\"H3068\"to|strong=\"H3068\"walk solicitous with|strong=\"H5973\"thy God|strong=\"H0430\".",
      "9": "The|strong=\"H8085\"voice|strong=\"H6963\"of|strong=\"H3068\"the|strong=\"H8085\"Lord|strong=\"H3068\"crieth to|strong=\"H3068\"the|strong=\"H8085\"city|strong=\"H5892\", and|strong=\"H3068\"salvation shall|strong=\"H3068\"be|strong=\"H8034\"to|strong=\"H3068\"them|strong=\"H7121\"that|strong=\"H8085\"fear|strong=\"H3372\"thy name|strong=\"H8034\": hear|strong=\"H8085\", O|strong=\"H3068\"ye tribes|strong=\"H4294\", and|strong=\"H3068\"who|strong=\"H4310\"shall|strong=\"H3068\"approve it|strong=\"H7121\"?",
      "10": "As|strong=\"H1004\"yet|strong=\"H5750\"there is|strong=\"H7563\"a|strong=\"H5750\"fire in|strong=\"H1004\"the|strong=\"H5750\"house|strong=\"H1004\"of|strong=\"H1004\"the|strong=\"H5750\"wicked|strong=\"H7563\", the|strong=\"H5750\"treasures|strong=\"H0214\"of|strong=\"H1004\"iniquity, and|strong=\"H1004\"a|strong=\"H5750\"scant measure|strong=\"H0374\"full of|strong=\"H1004\"wrath.",
      "11": "Shall|strong=\"H0068\"I|strong=\"H2135\"justify|strong=\"H2135\"wicked|strong=\"H7562\"balances|strong=\"H3976\", and|strong=\"H0068\"the deceitful|strong=\"H4820\"weights|strong=\"H0068\"of|strong=\"H0068\"the bag|strong=\"H3599\"?",
      "12": "By|strong=\"H3427\"which|strong=\"H0834\"her|strong=\"H4390\"rich|strong=\"H6223\"men|strong=\"H6223\"were|strong=\"H0834\"filled|strong=\"H4390\"with|strong=\"H4390\"iniquity, and|strong=\"H6310\"the|strong=\"H0834\"inhabitants|strong=\"H3427\"thereof have|strong=\"H0834\"spoken|strong=\"H1696\"lies|strong=\"H8267\", and|strong=\"H6310\"their|strong=\"H4390\"tongue|strong=\"H3956\"was|strong=\"H0834\"deceitful|strong=\"H8267\"in|strong=\"H3427\"their|strong=\"H4390\"mouth|strong=\"H6310\".",
      "13": "And|strong=\"H8074\"I|strong=\"H0589\"therefore|strong=\"H1571\"began to|strong=\"H5921\"strike|strong=\"H5221\"thee with|strong=\"H5921\"desolation|strong=\"H8074\"for|strong=\"H5921\"thy sins|strong=\"H2403\".",
      "14": "Thou shalt eat|strong=\"H0398\", but|strong=\"H3808\"shalt not|strong=\"H3808\"be|strong=\"H3808\"filled|strong=\"H7646\": and|strong=\"H0398\"thy humiliation shall|strong=\"H3808\"be|strong=\"H3808\"in|strong=\"H7130\"the|strong=\"H0834\"midst|strong=\"H7130\"of|strong=\"H7130\"thee: and|strong=\"H0398\"thou shalt take|strong=\"H5414\"hold|strong=\"H5414\", but|strong=\"H3808\"shalt not|strong=\"H3808\"save: and|strong=\"H0398\"those|strong=\"H0834\"whom|strong=\"H0834\"thou shalt save, I|strong=\"H0834\"will|strong=\"H0834\"give|strong=\"H5414\"up|strong=\"H5414\"to|strong=\"H5414\"the|strong=\"H0834\"sword|strong=\"H2719\".",
      "15": "Thou shalt sow|strong=\"H2232\", but|strong=\"H3808\"shalt not|strong=\"H3808\"reap|strong=\"H7114\": thou shalt tread|strong=\"H1869\"the|strong=\"H3808\"olives|strong=\"H2132\", but|strong=\"H3808\"shalt not|strong=\"H3808\"be|strong=\"H3808\"anointed with|strong=\"H8081\"the|strong=\"H3808\"oil|strong=\"H8081\": and|strong=\"H8081\"the|strong=\"H3808\"new|strong=\"H8492\"wine|strong=\"H3196\", but|strong=\"H3808\"shalt not|strong=\"H3808\"drink|strong=\"H8354\"the|strong=\"H3808\"wine|strong=\"H3196\".",
      "16": "For|strong=\"H4616\"thou hast kept|strong=\"H8104\"the|strong=\"H3605\"statutes|strong=\"H2708\"of|strong=\"H1004\"Amri, and|strong=\"H1004\"all|strong=\"H3605\"the|strong=\"H3605\"works|strong=\"H4639\"of|strong=\"H1004\"the|strong=\"H3605\"house|strong=\"H1004\"of|strong=\"H1004\"Achab: and|strong=\"H1004\"thou hast walked according to|strong=\"H5414\"their|strong=\"H3605\"wills, that|strong=\"H3605\"I|strong=\"H5414\"should|strong=\"H8104\"make|strong=\"H5414\"thee a|strong=\"H5414\"desolation|strong=\"H8047\", and|strong=\"H1004\"the|strong=\"H3605\"inhabitants|strong=\"H3427\"thereof a|strong=\"H5414\"hissing|strong=\"H8322\", and|strong=\"H1004\"you|strong=\"H5414\"shall|strong=\"H1004\"bear|strong=\"H5375\"the|strong=\"H3605\"reproach|strong=\"H2781\"of|strong=\"H1004\"my|strong=\"H3605\"people|strong=\"H5971\"."
    },
    "7": {
      "1": "Woe|strong=\"H0480\"is|strong=\"H0369\"me|strong=\"H5315\", for|strong=\"H3588\"I|strong=\"H3588\"am|strong=\"H1961\"become|strong=\"H1961\"as|strong=\"H1961\"one|strong=\"H0369\"that|strong=\"H3588\"gleaneth in|strong=\"H5315\"autumn the|strong=\"H3588\"grapes of|strong=\"H5315\"the|strong=\"H3588\"vintage|strong=\"H1210\": there|strong=\"H0369\"is|strong=\"H0369\"no|strong=\"H0369\"cluster|strong=\"H0811\"to|strong=\"H1961\"eat|strong=\"H0398\", my|strong=\"H1961\"soul|strong=\"H5315\"desired|strong=\"H0183\"the|strong=\"H3588\"firstripe figs.",
      "2": "The|strong=\"H3605\"holy|strong=\"H2623\"man|strong=\"H0376\"is|strong=\"H0369\"perished|strong=\"H0006\"out|strong=\"H4480\"of|strong=\"H0776\"the|strong=\"H3605\"earth|strong=\"H0776\", and|strong=\"H0776\"there|strong=\"H0369\"is|strong=\"H0369\"none|strong=\"H0369\"upright|strong=\"H3477\"among|strong=\"H4480\"men|strong=\"H0376\": they|strong=\"H0376\"all|strong=\"H3605\"lie|strong=\"H0693\"in|strong=\"H0776\"wait|strong=\"H0693\"for|strong=\"H0776\"blood|strong=\"H1818\", every|strong=\"H3605\"one|strong=\"H0376\"hunteth his|strong=\"H3605\"brother|strong=\"H0251\"to|strong=\"H0369\"death|strong=\"H1818\".",
      "3": "The|strong=\"H5921\"evil|strong=\"H7451\"of|strong=\"H8269\"their|strong=\"H5921\"hands|strong=\"H3709\"they|strong=\"H5921\"call good|strong=\"H3190\": the|strong=\"H5921\"prince|strong=\"H8269\"requireth, and|strong=\"H1419\"the|strong=\"H5921\"judge|strong=\"H8199\"is|strong=\"H1931\"for|strong=\"H5921\"giving|strong=\"H1696\": and|strong=\"H1419\"the|strong=\"H5921\"great|strong=\"H1419\"man|strong=\"H5315\"hath uttered|strong=\"H1696\"the|strong=\"H5921\"desire|strong=\"H5315\"of|strong=\"H8269\"his|strong=\"H5921\"soul|strong=\"H5315\", and|strong=\"H1419\"they|strong=\"H5921\"have|strong=\"H1696\"troubled it|strong=\"H1931\".",
      "4": "He|strong=\"H3117\"that|strong=\"H3117\"is|strong=\"H3117\"best|strong=\"H2896\"among them|strong=\"H0935\", is|strong=\"H3117\"as|strong=\"H1961\"a|strong=\"H1961\"brier: and|strong=\"H0935\"he|strong=\"H3117\"that|strong=\"H3117\"is|strong=\"H3117\"righteous, as|strong=\"H1961\"the|strong=\"H0935\"thorn|strong=\"H4534\"of|strong=\"H3117\"the|strong=\"H0935\"hedge|strong=\"H4534\". The|strong=\"H0935\"day|strong=\"H3117\"of|strong=\"H3117\"thy inspection, thy visitation cometh: now|strong=\"H6258\"shall|strong=\"H3117\"be|strong=\"H1961\"their|strong=\"H0935\"destruction.",
      "5": "Believe|strong=\"H0539\"not|strong=\"H0408\"a|strong=\"H7453\"friend|strong=\"H7453\", and|strong=\"H6310\"trust|strong=\"H0982\"not|strong=\"H0408\"in|strong=\"H0982\"a|strong=\"H7453\"prince: keep|strong=\"H8104\"the|strong=\"H8104\"doors|strong=\"H6607\"of|strong=\"H6310\"thy mouth|strong=\"H6310\"from|strong=\"H8104\"her|strong=\"H8104\"that|strong=\"H0539\"sleepeth in|strong=\"H0982\"thy bosom|strong=\"H2436\".",
      "6": "For|strong=\"H3588\"the|strong=\"H3588\"son|strong=\"H1121\"dishonoureth the|strong=\"H3588\"father|strong=\"H0001\", and|strong=\"H1121\"the|strong=\"H3588\"daughter|strong=\"H1323\"riseth up|strong=\"H6965\"against|strong=\"H0376\"her|strong=\"H3588\"mother|strong=\"H0517\", the|strong=\"H3588\"daughter|strong=\"H1323\"in|strong=\"H1004\"law against|strong=\"H0376\"her|strong=\"H3588\"mother|strong=\"H0517\"in|strong=\"H1004\"law: and|strong=\"H1121\"a|strong=\"H3588\"man’s|strong=\"H0376\"enemies|strong=\"H0341\"are|strong=\"H0376\"they|strong=\"H3588\"of|strong=\"H1121\"his|strong=\"H0376\"own|strong=\"H0376\"household|strong=\"H1004\".",
      "7": "But|strong=\"H8085\"I|strong=\"H0589\"will|strong=\"H3068\"look towards the|strong=\"H8085\"Lord|strong=\"H3068\", I|strong=\"H0589\"will|strong=\"H3068\"wait|strong=\"H3176\"for|strong=\"H3068\"God|strong=\"H0430\"my|strong=\"H8085\"Saviour: my|strong=\"H8085\"God|strong=\"H0430\"will|strong=\"H3068\"hear|strong=\"H8085\"me|strong=\"H0589\".",
      "8": "Rejoice|strong=\"H8055\"not|strong=\"H0408\", thou, my|strong=\"H3068\"enemy|strong=\"H0341\", over|strong=\"H5307\"me|strong=\"H8055\", because|strong=\"H3588\"I|strong=\"H3588\"am|strong=\"H3068\"fallen|strong=\"H5307\": I|strong=\"H3588\"shall|strong=\"H3068\"arise|strong=\"H6965\", when|strong=\"H3588\"I|strong=\"H3588\"sit|strong=\"H3427\"in|strong=\"H3427\"darkness|strong=\"H2822\", the|strong=\"H3588\"Lord|strong=\"H3068\"is|strong=\"H3068\"my|strong=\"H3068\"light|strong=\"H0216\".",
      "9": "I|strong=\"H0834\"will|strong=\"H3068\"bear|strong=\"H5375\"the|strong=\"H0834\"wrath|strong=\"H2197\"of|strong=\"H3068\"the|strong=\"H0834\"Lord|strong=\"H3068\", because|strong=\"H3588\"I|strong=\"H0834\"have|strong=\"H0834\"sinned|strong=\"H2398\"against|strong=\"H2398\"him|strong=\"H7200\"; until|strong=\"H5704\"he|strong=\"H0834\"judge|strong=\"H7378\"my|strong=\"H3068\"cause|strong=\"H7379\"and|strong=\"H3068\"execute judgment|strong=\"H4941\"for|strong=\"H3588\"me|strong=\"H7200\": he|strong=\"H0834\"will|strong=\"H3068\"bring|strong=\"H3318\"me|strong=\"H7200\"forth|strong=\"H3318\"into|strong=\"H3318\"the|strong=\"H0834\"light|strong=\"H0216\", I|strong=\"H0834\"shall|strong=\"H3068\"behold|strong=\"H7200\"his|strong=\"H3068\"justice|strong=\"H4941\".",
      "10": "And|strong=\"H3068\"my|strong=\"H3068\"enemy|strong=\"H0341\"shall|strong=\"H3068\"behold|strong=\"H7200\", and|strong=\"H3068\"she shall|strong=\"H3068\"be|strong=\"H1961\"covered|strong=\"H3680\"with|strong=\"H0413\"shame|strong=\"H0955\", who|strong=\"H3068\"saith to|strong=\"H0413\"me|strong=\"H0413\": Where|strong=\"H0346\"is|strong=\"H3068\"the|strong=\"H0559\"Lord|strong=\"H3068\"thy God|strong=\"H0430\"? My|strong=\"H3068\"eyes|strong=\"H5869\"shall|strong=\"H3068\"look|strong=\"H7200\"down|strong=\"H4823\"upon|strong=\"H1961\"her|strong=\"H0413\": now|strong=\"H6258\"shall|strong=\"H3068\"she be|strong=\"H1961\"trodden under foot as|strong=\"H1961\"the|strong=\"H0559\"mire|strong=\"H2916\"of|strong=\"H0430\"the|strong=\"H0559\"streets|strong=\"H2351\".",
      "11": "The|strong=\"H3117\"day|strong=\"H3117\"shall|strong=\"H3117\"come, that|strong=\"H3117\"thy walls|strong=\"H1447\"may|strong=\"H1931\"be|strong=\"H3117\"built|strong=\"H1129\"up|strong=\"H1129\": in|strong=\"H3117\"that|strong=\"H3117\"day|strong=\"H3117\"shall|strong=\"H3117\"the|strong=\"H3117\"law be|strong=\"H3117\"far|strong=\"H7368\"removed|strong=\"H7368\".",
      "12": "In|strong=\"H0935\"that|strong=\"H3117\"day|strong=\"H3117\"they|strong=\"H3117\"shall|strong=\"H3117\"come|strong=\"H0935\"even|strong=\"H5704\"from|strong=\"H4480\"Assyria|strong=\"H0804\"to|strong=\"H0935\"thee, and|strong=\"H0935\"to|strong=\"H0935\"the|strong=\"H0935\"fortified|strong=\"H4692\"cities|strong=\"H5892\": and|strong=\"H0935\"from|strong=\"H4480\"the|strong=\"H0935\"fortified|strong=\"H4692\"cities|strong=\"H5892\"even|strong=\"H5704\"to|strong=\"H0935\"the|strong=\"H0935\"river|strong=\"H5104\", and|strong=\"H0935\"from|strong=\"H4480\"sea|strong=\"H3220\"to|strong=\"H0935\"sea|strong=\"H3220\", and|strong=\"H0935\"from|strong=\"H4480\"mountain|strong=\"H2022\"to|strong=\"H0935\"mountain|strong=\"H2022\".",
      "13": "And|strong=\"H0776\"the|strong=\"H5921\"land|strong=\"H0776\"shall|strong=\"H0776\"be|strong=\"H1961\"made|strong=\"H1961\"desolate|strong=\"H8077\", because|strong=\"H5921\"of|strong=\"H0776\"the|strong=\"H5921\"inhabitants|strong=\"H3427\"thereof, and|strong=\"H0776\"for|strong=\"H5921\"the|strong=\"H5921\"fruit|strong=\"H6529\"of|strong=\"H0776\"their|strong=\"H5921\"devices.",
      "14": "Feed|strong=\"H7462\"thy people|strong=\"H5971\"with|strong=\"H3117\"thy rod|strong=\"H7626\", the|strong=\"H3117\"flock|strong=\"H6629\"of|strong=\"H3117\"thy inheritance|strong=\"H5159\", them|strong=\"H8432\"that|strong=\"H3117\"dwell|strong=\"H7931\"alone|strong=\"H0910\"in|strong=\"H7931\"the|strong=\"H3117\"forest|strong=\"H3293\", in|strong=\"H7931\"the|strong=\"H3117\"midst|strong=\"H8432\"of|strong=\"H3117\"Carmel|strong=\"H3760\": they|strong=\"H3117\"shall|strong=\"H3117\"feed|strong=\"H7462\"in|strong=\"H7931\"Basan and|strong=\"H3117\"Galaad according to|strong=\"H3117\"the|strong=\"H3117\"days|strong=\"H3117\"of|strong=\"H3117\"old|strong=\"H5769\".",
      "15": "According to|strong=\"H4714\"the|strong=\"H7200\"days|strong=\"H3117\"of|strong=\"H0776\"thy coming|strong=\"H3318\"out|strong=\"H3318\"of|strong=\"H0776\"the|strong=\"H7200\"land|strong=\"H0776\"of|strong=\"H0776\"Egypt|strong=\"H4714\"I|strong=\"H3117\"will|strong=\"H0776\"shew him|strong=\"H7200\"wonders|strong=\"H6381\".",
      "16": "The|strong=\"H3605\"nations|strong=\"H1471\"shall|strong=\"H1471\"see|strong=\"H7200\", and|strong=\"H3027\"shall|strong=\"H1471\"be|strong=\"H3027\"confounded|strong=\"H0954\"at|strong=\"H5921\"all|strong=\"H3605\"their|strong=\"H3605\"strength|strong=\"H1369\": they|strong=\"H5921\"shall|strong=\"H1471\"put|strong=\"H7760\"the|strong=\"H3605\"hand|strong=\"H3027\"upon|strong=\"H5921\"the|strong=\"H3605\"mouth|strong=\"H6310\", their|strong=\"H3605\"ears|strong=\"H0241\"shall|strong=\"H1471\"be|strong=\"H3027\"deaf.",
      "17": "They|strong=\"H3068\"shall|strong=\"H3068\"lick|strong=\"H3897\"the|strong=\"H0413\"dust|strong=\"H6083\"like|strong=\"H0776\"serpents|strong=\"H5175\", as|strong=\"H3068\"the|strong=\"H0413\"creeping things of|strong=\"H0776\"the|strong=\"H0413\"earth|strong=\"H0776\", they|strong=\"H3068\"shall|strong=\"H3068\"be|strong=\"H3068\"disturbed|strong=\"H7264\"in|strong=\"H0413\"their|strong=\"H3068\"houses: they|strong=\"H3068\"shall|strong=\"H3068\"dread|strong=\"H6342\"the|strong=\"H0413\"Lord|strong=\"H3068\"our|strong=\"H3068\"God|strong=\"H0430\", and|strong=\"H3068\"shall|strong=\"H3068\"fear|strong=\"H3372\"thee.",
      "18": "Who|strong=\"H4310\"is|strong=\"H1931\"a|strong=\"H3588\"God|strong=\"H0410\"like|strong=\"H3644\"to|strong=\"H5921\"thee, who|strong=\"H4310\"takest away|strong=\"H5375\"iniquity|strong=\"H5771\", and|strong=\"H2388\"passest by|strong=\"H5921\"the|strong=\"H5921\"sin|strong=\"H5771\"of|strong=\"H5921\"the|strong=\"H5921\"remnant|strong=\"H7611\"of|strong=\"H5921\"thy inheritance|strong=\"H5159\"? he|strong=\"H1931\"will|strong=\"H4310\"send his|strong=\"H5921\"fury in|strong=\"H5921\"no|strong=\"H3808\"more|strong=\"H3808\", because|strong=\"H3588\"he|strong=\"H1931\"delighteth in|strong=\"H5921\"mercy.",
      "19": "He|strong=\"H7725\"will|strong=\"H3220\"turn|strong=\"H7725\"again|strong=\"H7725\", and|strong=\"H7725\"have|strong=\"H7355\"mercy|strong=\"H7355\"on|strong=\"H7355\"us|strong=\"H7725\": he|strong=\"H7725\"will|strong=\"H3220\"put|strong=\"H7725\"away|strong=\"H7725\"our|strong=\"H3605\"iniquities|strong=\"H5771\": and|strong=\"H7725\"he|strong=\"H7725\"will|strong=\"H3220\"cast|strong=\"H7993\"all|strong=\"H3605\"our|strong=\"H3605\"sins|strong=\"H2403\"into|strong=\"H7993\"the|strong=\"H3605\"bottom of|strong=\"H3605\"the|strong=\"H3605\"sea|strong=\"H3220\".",
      "20": "Thou wilt perform the|strong=\"H0834\"truth|strong=\"H0571\"of|strong=\"H3117\"Jacob|strong=\"H3290\", the|strong=\"H0834\"mercy to|strong=\"H5414\"Abraham|strong=\"H0085\": which|strong=\"H0834\"thou hast sworn|strong=\"H7650\"to|strong=\"H5414\"our|strong=\"H5414\"fathers|strong=\"H0001\"from|strong=\"H3117\"the|strong=\"H0834\"days|strong=\"H3117\"of|strong=\"H3117\"old."
    }
  }
}