{"2": {"16": [{"type": "allusion", "target": "John 10:14", "note": "My beloved is mine and I am his — the mutual possession of the beloved and the lover; I know my sheep and my sheep know me (John 10:14) is the new covenant expression of the same mutual-knowing/belonging that the Song celebrates; Christ's love for the church is the fulfillment of the Song's bridegroom love"}]}, "8": {"6": [{"type": "allusion", "target": "Rom 8:35-39", "note": "Love is strong as death, jealousy is fierce as the grave; its flashes are flashes of fire, the very flame of the LORD — the Song's declaration of love's unconquerable strength; Paul's conviction that nothing can separate us from the love of God in Christ Jesus is the new covenant answer to the Song's vision of love stronger than death: Christ's love has defeated death itself and remains unbreakable"}]}}