{"code":"H216","lemma":"אוֹר","translit":"ʼôwr","gloss":"bright, clear, [phrase] day, light (-ning), morning, sun.","count":112,"refs":["Genesis 1:3-5","Genesis 1:18","Exodus 10:23","Judges 16:2","Judges 19:26","1 Samuel 14:36","1 Samuel 25:22","1 Samuel 25:34","1 Samuel 25:36","2 Samuel 17:22","2 Samuel 23:4","2 Kings 7:9","Nehemiah 8:3","Job 3:9","Job 3:16","Job 3:20","Job 12:22","Job 12:25","Job 17:12","Job 18:5-6","Job 18:18","Job 22:28","Job 24:13-14","Job 24:16","Job 25:3","Job 26:10","Job 28:11","Job 29:3","Job 29:24","Job 30:26","Job 31:26","Job 33:28","Job 33:30","Job 36:30","Job 36:32","Job 37:3","Job 37:11","Job 37:15","Job 37:21","Job 38:15","Job 38:19","Job 38:24","Job 41:18","Psalms 4:6","Psalms 27:1","Psalms 36:9","Psalms 37:6","Psalms 38:10","Psalms 43:3","Psalms 44:3","Psalms 49:19","Psalms 56:13","Psalms 78:14","Psalms 89:15","Psalms 97:11","Psalms 104:2","Psalms 112:4","Psalms 119:105","Psalms 136:7","Psalms 139:11","Psalms 148:3","Proverbs 4:18","Proverbs 6:23","Proverbs 13:9","Proverbs 16:15","Ecclesiastes 2:13","Ecclesiastes 11:7","Ecclesiastes 12:2","Isaiah 2:5","Isaiah 5:20","Isaiah 5:30","Isaiah 9:2","Isaiah 10:17","Isaiah 13:10","Isaiah 18:4","Isaiah 30:26","Isaiah 42:6","Isaiah 42:16","Isaiah 45:7","Isaiah 49:6","Isaiah 51:4","Isaiah 58:8","Isaiah 58:10","Isaiah 59:9","Isaiah 60:1","Isaiah 60:3","Isaiah 60:19-20","Jeremiah 4:23","Jeremiah 13:16","Jeremiah 25:10","Jeremiah 31:35","Lamentations 3:2","Ezekiel 32:7-8","Hosea 6:5","Amos 5:18","Amos 5:20","Amos 8:8-9","Micah 2:1","Micah 7:8-9","Habakkuk 3:4","Habakkuk 3:11","Zephaniah 3:5","Zechariah 14:6-7"]}